Workbook

Sheet Dashboard
A1: NEOPRO SAFe Portfolio Dashboard
A3: PORTFOLIO OVERVIEW
A4: Epics | B4: =COUNTA('Epics & LBC'!A4:A50) -> 21 | C4: Features | D4: =COUNTIF('Features & US'!B5:B100,"F-*") -> 35 | E4: User Stories | F4: =COUNTA('User Stories'!A5:A500) -> 256 | G4: Total SP | H4: =SUM('User Stories'!E5:E500) -> 821
A5: SP PI-1 | B5: =SUMIF('Features & US'!I5:I100,"PI-1*",'Features & US'!E5:E100) -> 134 | C5: SP PI-2 | D5: =SUMIF('Features & US'!I5:I100,"PI-2*",'Features & US'!E5:E100) -> 61 | E5: SP PI-3 | F5: =SUMIF('Features & US'!I5:I100,"PI-3*",'Features & US'!E5:E100) -> 51 | G5: ARR (K€) | H5: 350
A7: EPICS STATUS | C7: FEATURES STATUS | E7: RISKS (ROAM) | G7: FLOW DISTRIBUTION
E8: → Inspect & Adapt
A9: En cours | B9: =COUNTIF('Epics & LBC'!G4:G50,"En cours") -> 2 | C9: Terminé | D9: =COUNTIF('Features & US'!G5:G100,"Terminé") -> 9 | E9: Active | F9: =COUNTIF(ROAM!C5:C12,"Accepté")+COUNTIF(ROAM!C5:C12,"Pris en charge") -> 6 | G9: Monétisation | H9: =COUNTIF('Epics & LBC'!$D$4:$D$24,"TS1*")/COUNTA('Epics & LBC'!$A$4:$A$24) -> 0.28571429
A10: Terminé | B10: =COUNTIF('Epics & LBC'!G4:G50,"Terminé") -> 3 | C10: Backlog | D10: =COUNTIF('Features & US'!G5:G100,"Backlog") -> 26 | E10: Atténué | F10: =COUNTIF(ROAM!C5:C12,"Atténué") -> 2 | G10: Exp. Match | H10: =COUNTIF('Epics & LBC'!$D$4:$D$24,"TS2*")/COUNTA('Epics & LBC'!$A$4:$A$24) -> 0.33333333
A11: Backlog | B11: =COUNTIF('Epics & LBC'!G4:G50,"Backlog") -> 16 | C11: En cours | D11: =COUNTIF('Features & US'!G5:G100,"En cours") -> 0 | E11: Résolu | F11: =COUNTIF(ROAM!C5:C12,"Résolu") -> 0 | G11: Acquisition | H11: =COUNTIF('Epics & LBC'!$D$4:$D$24,"TS3*")/COUNTA('Epics & LBC'!$A$4:$A$24) -> 0.14285714
A12: Total | B12: =SUM(B9:B11) -> 21 | C12: Total | D12: =SUM(D9:D11) -> 35 | E12: Total | F12: =COUNTA(ROAM!A5:A12) -> 8 | G12: Excellence Ops | H12: =COUNTIF('Epics & LBC'!$D$4:$D$24,"TS4*")/COUNTA('Epics & LBC'!$A$4:$A$24) -> 0.23809524
A14: ROADMAP SUMMARY
A15: PI | B15: Période | C15: Initiatives clés | G15: Planned SP | H15: Status
A16: PI-1 | B16: Fév-Mar 2026 | C16: Sponsors + Analytics + Onboarding + Résilience WiFi | G16: =B5 -> 134 | H16: 🟢 Active
A17: PI-2 | B17: Avr-Mai 2026 | C17: Régie + Motion + Email + Score API Fédérations | G17: =D5 -> 61 | H17: 🟡 Planned
A18: PI-3 | B18: Juin-Juil 2026 | C18: Multi-écrans + Marque blanche + Billetterie + ML + OAuth | G18: =F5 -> 51 | H18: ⚪ Backlog
A20: SPRINT VELOCITY (PI-1)
A21: Sprint | B21: S1 | C21: S2 | D21: S3 | E21: Avg | F21: S5 | G21: S6 | H21: Avg
A22: Actual SP | B22: ='Sprint Tracker'!D6 -> 38 | C22: ='Sprint Tracker'!D7 -> 23 | D22: ='Sprint Tracker'!D8 -> 16 | E22: =IFERROR(AVERAGE(B22:D22),"-") -> 25.666667 | F22: =IF('Sprint Tracker'!D14="","-",'Sprint Tracker'!D14) -> 0 | G22: =IF('Sprint Tracker'!D15="","-",'Sprint Tracker'!D15) -> 0 | H22: =IFERROR(AVERAGE('Sprint Tracker'!D4:D7),0) -> 30.5
A24: NAVIGATION RAPIDE
A25: → Glossaire | E25: → Vision & OKR | G25: → Guide Gabin
A26: → Value Streams | E26: → Epics & LBC
A27: → Lean Business Cases | E27: → Features & US
A28: → PI Objectives | E28: → Sprint Tracker
A29: → ROAM | E29: → Inspect & Adapt
A30: → Flow Metrics | E30: → Implemented Backlog
A31: → User Stories | E31: → _Metadata

Sheet Guide
B1: GUIDE D'ONBOARDING — GABIN
B2: Bienvenue dans le Portfolio SAFe de NEOPRO ! Ce guide t'explique comment naviguer et utiliser ce fichier. | O2: ← Dashboard
B4: C'EST QUOI CE FICHIER ?
B5: Ce fichier Excel est le Portfolio SAFe (Scaled Agile Framework) de NEOPRO. C'est notre source unique de vérité pour piloter le produit : vision, objectifs, epics, features, user stories, suivi des sprints et métriques de performance.
B7: NOTRE CADRE SAFe SIMPLIFIÉ
B8: PI (Program Increment) | C8: Équipe | D8: Rythme | E8: Priorisation WSJF
B9: 6 semaines = 3 sprints de 2 semaines PI-1 : Fév-Mar 2026 PI-2 : Avr-Mai 2026 PI-3 : Juin-Juil 2026 | C9: Gwenvael (PO + Dev) Gabin (Dev) Solo-dev augmenté, pas de Scrum Master | D9: Sprint = 2 semaines Review chaque vendredi fin de sprint Inspect & Adapt en fin de PI | E9: WSJF = (BV + TC + RR) / Job Size Plus le score est élevé, plus c'est prioritaire
B11: CARTE DES FEUILLES — OÙ TROUVER QUOI
B12: Feuille | C12: Ce qu'elle contient | D12: Quand la consulter
B13: Dashboard | C13: Vue d'ensemble : KPIs, statuts, roadmap, vélocité | D13: Chaque matin — ton point de départ
B14: Glossaire | C14: Définitions des termes SAFe et NEOPRO | D14: Quand un terme te semble flou
B15: Vision & OKR | C15: Vision produit, mission, OKRs trimestriels | D15: Pour comprendre le "pourquoi"
B16: Value Streams | C16: Flux de valeur (VS1 Club→Screen, VS2 Sponsor→Impression) | D16: Pour comprendre l'architecture métier
B17: Epics & LBC | C17: Grands chantiers + scores WSJF + critères Go/No-Go | D17: Pour voir les gros chantiers en cours
B18: Lean Business Cases | C18: Justifications détaillées de chaque Epic | D18: Avant de démarrer un Epic
B19: Features & US | C19: Features avec décompte US, SP, statut, sprint | D19: Pour planifier ton sprint
B20: PI Objectives | C20: Objectifs engagés et étendus par PI | D20: En début de PI et en review
B21: Sprint Tracker | C21: SP planifiés vs réalisés, vélocité, burndown | D21: Chaque fin de sprint
B22: ROAM | C22: Risques : probabilité, impact, mitigation | D22: Quand tu sens un blocage
B23: Inspect & Adapt | C23: Rétrospective PI : features livrées, métriques, décisions | D23: En fin de PI
... B26: User Stories | C26: 250 US avec critères d'acceptation, SP, domaine | D26: Pour coder — ta source principale
B28: TON WORKFLOW QUOTIDIEN
B29: 1. Dashboard | C29: Checker les KPIs du jour, la vélocité, les risques
B30: 2. User Stories | C30: Trouver ta prochaine US (filtre Sprint + Statut = Backlog)
B31: 3. Critères d'acceptation | C31: Lire la colonne H de l'US pour savoir quoi implémenter
B32: 4. Code + PR | C32: Implémenter, tester, push. Conventional Commits : feat(scope): ...
B33: 5. Sprint Tracker | C33: Mettre à jour les SP réalisés en fin de sprint
B34: 6. ROAM | C34: Si blocage → ajouter un risque avec mitigation
B36: CONVENTIONS & LISTES DÉROULANTES
B37: Convention | C37: Valeurs | D37: Note
B38: Statuts | C38: Backlog → En cours → Terminé → Livré | D38: Progression standard d'un item
B39: Sprints | C39: S1, S2, S3 (par PI) — S4/S5/S6 pour PI-2/PI-3 | D39: Chaque PI a 3 sprints de 2 sem
B40: Priorité Features | C40: 1 = haute, 2 = moyenne, 3 = basse | D40: Numérique, pas MoSCoW
B41: SP (Story Points) | C41: Fibonacci : 1, 2, 3, 5, 8 | D41: Estime la complexité, pas le temps
B42: WSJF | C42: (BV + TC + RR) / Job Size | D42: Calculé auto dans Epics & LBC
B43: Domaines | C43: 12 domaines (Sponsors, Match, Réseau...) | D43: Dropdown dans User Stories col I
B44: ROAM | C44: Résolu / Accepté / Atténué / Pris en charge | D44: Classification des risques
B45: Listes liées | C45: Epic ID, Feature ID, VS, Thème | D45: Dropdown dynamiques cross-sheet
B47: CHIFFRES CLÉS À RETENIR
B48: 21 Epics | C48: 35 Features | D48: 250 User Stories | E48: 174 en prod
B49: 79 SP PI-1 | C49: 3 sprints / PI | D49: 2235 tests | E49: 50+ Pi en flotte
B51: LIENS RAPIDES
B52: ← Dashboard
B53: → User Stories (ta feuille principale)
B54: → Sprint Tracker
B55: → Features & US
B56: → ROAM (risques)
B57: → Implemented Backlog (ce qui existe)
B59: TIPS
B60: • Les cellules avec un petit triangle ont des listes déroulantes — clique dessus pour voir les options
B61: • Les liens bleus soulignés naviguent vers d'autres feuilles
B62: • Les formules se recalculent automatiquement — ne modifie pas les cellules avec des =
B63: • En cas de doute sur un terme → onglet Glossaire
... B65: • Ne jamais changer le format des api_key des sites (casserait tous les Pi)

Sheet Glossaire
A1: GLOSSAIRE SAFe — NEOPRO
A2: Terme | B2: Définition | O2: ← Dashboard
A3: Epic | B3: Grande initiative couvrant plusieurs Features, liée à une stratégie business
A4: Feature | B4: Bloc fonctionnel apportant valeur, découpé en User Stories
A5: User Story | B5: Récit utilisateur livrable en 1-2 sprints (taille ~5 SP)
A6: Story Point (SP) | B6: Unité de complexité relative (Fibonacci: 1,2,3,5,8...)
A7: Sprint | B7: Itération 2 semaines de travail continu
A8: PI (Program Increment) | B8: Période de 6 semaines = 3 sprints de 2 semaines (cadence NEOPRO)
A9: Value Stream | B9: Flux continu de création de valeur (OVS ou DVS)
A10: WSJF (Weighted Shortest Job First) | B10: Priorisation: (Business Value + Time Criticality) / Job Size
A11: MoSCoW | B11: Must (obligatoire), Should (important), Could (sympa), Won't (exclu)
A12: Lean Business Case | B12: Justification business simplifée (coût vs bénéfice)
A13: Critères d'acceptation | B13: Conditions pour que la US soit "Done" (définition
A14: Backlog | B14: Pile ordonnée de Features/US prêtes ou futures
... A25: I&A (Inspect & Adapt) | B25: Rétrospective SAFe collective tous les PIs

Sheet Vision & OKR
A1: NEOPRO — Vision, Thèmes Stratégiques & OKR 2026
O2: ← Dashboard
A3: Vision Produit
A5: Devenir le partenaire de référence des clubs sportifs amateurs en France pour professionnaliser leur expérience match et sécuriser leurs revenus.
A7: 4 Thèmes Stratégiques
A8: ID | B8: Thème | C8: Description | D8: OVS lié | E8: Horizon | F8: Poids budget
A9: TS-1 | B9: Monétisation Sponsors | C9: Maximiser les revenus sponsors par club via le ciblage local, les preuves de diffusion et le self-service annonceur | D9: OVS-2 | E9: PI-1 → PI-3 | F9: 35%
A10: TS-2 | B10: Expérience Match Live | C10: Offrir la meilleure expérience match jour (overlay multi-sport, timer, recording, phases) pour engager les clubs | D10: OVS-1 | E10: PI-1 → PI-2 | F10: 25%
A11: TS-3 | B11: Acquisition & Croissance | C11: Accélérer l'onboarding clubs (time-to-value <1j), réduire le churn (<5%/an), atteindre 100 clubs actifs | D11: OVS-1 + OVS-2 | E11: PI-2 → PI-3 | F11: 20%
A12: TS-4 | B12: Excellence Opérationnelle | C12: Garantir 99.5% uptime, <2h MTTR, monitoring proactif, OTA fiable, réseau résilient | D12: DVS-1 | E12: Continu | F12: 20%
A14: OKR 2026 — Objectifs & Key Results
A15: Obj # | B15: Objectif | C15: KR # | D15: Key Result | E15: Thème(s) | F15: Target
A16: O1 | B16: Faire de NEOPRO le partenaire de référence des clubs amateurs en Bretagne/Pays de Loire | C16: 1.1 | D16: 3 clubs beta convertis en payants | E16: TS-3 | F16: Q2 2026
C17: 1.2 | D17: 15 clubs payants actifs | E17: TS-3 | F17: Déc 2026
C18: 1.3 | D18: Taux de renouvellement >85% | E18: TS-3 | F18: Déc 2026
C19: 1.4 | D19: NPS clubs ≥8/10 | E19: TS-2, TS-3 | F19: Q4 2026
C20: 1.5 | D20: 2 partenariats ligues régionales signés | E20: TS-3 | F20: Q3 2026
C21: 1.6 | D21: 3 cas ROI sponsors documentés | E21: TS-1 | F21: Q3 2026
C22: 1.7 | D22: 6 annonceurs régionaux actifs | E22: TS-1 | F22: Q4 2026
C23: 1.8 | D23: ARPU annonceur >300€/mois | E23: TS-1 | F23: Q4 2026
A24: O2 | B24: Créer une expérience match que les clubs ne peuvent plus quitter | C24: 2.1 | D24: Taux d'utilisation 100% des matchs à domicile | E24: TS-2 | F24: Q4 2026
C25: 2.2 | D25: Latence télécommande <200ms local / <2s cloud | E25: TS-2 | F25: Q1 2026
C26: 2.3 -> a suppr | D26: 6 sports supportés en overlay | E26: TS-2 | F26: ✅ Done
C27: 2.4 | D27: Score CSAT bénévole >4.5/5 | E27: TS-2 | F27: Q3 2026
C28: 2.5 | D28: Taux activation >80% (1er match dans les 7 jours) | E28: TS-2, TS-3 | F28: Continu
C29: 2.6 | D29: 0 incident bloquant pendant un match | E29: TS-2, TS-4 | F29: Continu
C30: 2.7 | D30: Temps d'installation <4h par club | E30: TS-2, TS-4 | F30: Q2 2026
A31: O3 | B31: Bâtir un réseau de clubs qui tire la croissance | C31: 3.1 | D31: 30% des nouveaux clubs via referral | E31: TS-3 | F31: Q4 2026
C32: 3.2 | D32: 10 témoignages vidéo clubs | E32: TS-3 | F32: Q3 2026
C33: 3.3 | D33: 2 clubs ambassadeurs officiels par région | E33: TS-3 | F33: Q4 2026
C34: 3.4 | D34: 15 prospects qualifiés via réseau | E34: TS-3 | F34: Q3 2026
C35: 3.5 | D35: Présence dans 2 médias sportifs régionaux | E35: TS-3 | F35: Q3 2026
C36: 3.6 | D36: 1 partenariat tournoi majeur | E36: TS-3 | F36: Q4 2026
C37: 3.7 | D37: NPS ≥50 | E37: TS-3 | F37: Q4 2026
C38: 3.8 | D38: 25 clubs onboardés en Q1-Q2 | E38: TS-3 | F38: Juin 2026
A39: O4 | B39: Garantir une infrastructure fiable à la hauteur de l'ambition | C39: 4.1 | D39: Uptime API 99.5% | E39: TS-4 | F39: Continu
C40: 4.2 | D40: MTTR incident <2h | E40: TS-4 | F40: Continu
C41: 4.3 | D41: 0 perte de données vidéo/config (checksum SHA-256) | E41: TS-4 | F41: Continu
C42: 4.4 | D42: OTA success rate >95% | E42: TS-4 | F42: Q2 2026
C43: 4.5 | D43: Temps de résolution support <24h | E43: TS-4 | F43: Continu
C44: 4.6 | D44: Monitoring proactif en place (alertes automatiques) | E44: TS-4 | F44: Q2 2026
C45: 4.7 | D45: Procédure d'installation documentée reproductible sans Gwenvael | E45: TS-4 | F45: Q2 2026
A46: O5 | B46: Construire un produit scalable sans dette technique | C46: 5.1 | D46: API partenaires <100ms p95 | E46: TS-4 | F46: Q4 2026
C47: 5.2 | D47: Tests coverage >75% (actuellement ~2387 tests) | E47: TS-4 | F47: Q3 2026
C48: 5.3 | D48: Pipeline CI <5min | E48: TS-4 | F48: Q2 2026
C49: 5.4 | D49: 0 vulnérabilité critique non patchée sous 48h | E49: TS-4 | F49: Continu
C50: 5.5 | D50: Documentation technique à jour pour 100% des endpoints | E50: TS-4 | F50: Q3 2026
C51: 5.6 | D51: Temps d'onboarding dev externe <1 jour | E51: TS-4 | F51: Q3 2026
C52: 5.7 | D52: Architecture supportant 200 clubs sans refonte | E52: TS-4 | F52: Q4 2026
C53: 5.8 | D53: Roadmap produit Q3-Q4 2026 définie et priorisée | E53: TS-4 | F53: Q2 2026
A55: Total: 5 Objectifs, 38 Key Results
A57: KPI Actuels (Fév 2026)
A58: KPI | B58: Valeur actuelle | C58: Target | D58: Statut | E58: Source
A59: Clubs actifs (Pi connectés) | B59: 4 | C59: 100 | D59: 🟡 En cours | E59: Dashboard fleet
A60: Annonceurs actifs | B60: 0 | C60: 10 | D60: 🟡 Early stage | E60: DB advertisers
A61: Tests totaux | B61: 2 387 | C61: 2 500 | D61: 🟢 On track | E61: npm run test:*
A62: Uptime API | B62: 99.2% | C62: 99.5% | D62: 🟡 Proche | E62: Grafana
A63: Versions livrées | B63: 30+ (v3.47→v3.60) | C63: Continu | D63: 🟢 Actif | E63: Git tags
A64: Features implémentées (Impl. Backlog) | B64: 174 | C64: - | D64: 🟢 Complet | E64: IMPLEMENTED-BACKLOG

Sheet Value Streams
A1: NEOPRO — Value Streams & Flux de Valeur
O2: ← Dashboard
A3: Outcome Value Streams (OVS)
A4: ID | B4: Value Stream | C4: Trigger | D4: Value Delivered | E4: Key Steps | F4: Lead Time | G4: Bottleneck
A5: OVS-1 | B5: Club to Screen | C5: Club signe contrat | D5: Vidéos diffusées sur TV dans le gymnase | E5: Onboarding → Config → Upload → Deploy → Diffusion | F5: < 1 jour (target) | G5: Installation physique Pi
A6: OVS-2 | B6: Sponsor to Impression | C6: Annonceur signe contrat | D6: Impressions pub mesurées et certifiées | E6: Signup → Upload pub → Association sites → Diffusion → Report | F6: < 2 jours | G6: Association manuelle site-sponsor
A8: OVS-1 — Club to Screen (détail)
A9: # | B9: Step | C9: Outil | D9: Owner | E9: Durée | F9: Input | G9: Output
A10: 1 | B10: Vente & signature | C10: CRM (externe) | D10: Commercial | E10: 1-2 semaines | F10: Lead club | G10: Contrat signé + abonnement
A11: 2 | B11: Installation Pi dans le club | C11: Toolbox Déploiement | D11: Technicien | E11: 1-2 heures | F11: Pi + TV + SD card | G11: Pi connecté au Dashboard
A12: 3 | B12: Configuration club | C12: Dashboard Admin | D12: Opérateur | E12: 15 min | F12: Logo, catégories, sponsors | G12: Config déployée sur Pi
A13: 4 | B13: Upload vidéos contenu | C13: Dashboard Admin | D13: Opérateur | E13: 10 min | F13: Fichiers vidéo | G13: Vidéos sur FTP + checksum
A14: 5 | B14: Déploiement vers Pi | C14: Central Server → Sync Agent | D14: Automatisé | E14: 2-5 min | F14: Commande deploy | G14: Vidéos sur disque Pi
A15: 6 | B15: Diffusion sur TV | C15: TV Player | D15: Automatisé | E15: Immédiat | F15: Config + vidéos | G15: Boucle vidéo diffusée
A16: 7 | B16: Match day (bénévole) | C16: Télécommande | D16: Staff club | E16: Durée match | F16: QR code / URL | G16: Score live + phases + recording
A17: 8 | B17: Analytics & rapports | C17: Dashboard + PDF | D17: Automatisé | E17: Quotidien | F17: Impressions brutes | G17: Stats club + sponsor
A19: OVS-2 — Sponsor to Impression (détail)
A20: # | B20: Step | C20: Outil | D20: Owner | E20: Durée | F20: Input | G20: Output
A21: 1 | B21: Inscription annonceur | C21: Portail Annonceur / Magic Link | D21: Annonceur | E21: 5 min | F21: Email + vidéo pub | G21: Compte créé + vidéo uploadée
A22: 2 | B22: Association site-sponsor | C22: Dashboard Admin | D22: Opérateur | E22: 2 min | F22: Sponsor + sites cibles | G22: Mapping sponsor→sites
A23: 3 | B23: Sync sponsors vers Pi | C23: Central Server → Sync Agent | D23: Automatisé | E23: 2-5 min | F23: Config updated | G23: Sponsors sur disque Pi
A24: 4 | B24: Diffusion pub sur TV | C24: TV Player | D24: Automatisé | E24: Immédiat | F24: Boucle vidéo avec pubs | G24: Impressions trackées
A25: 5 | B25: Tracking impressions | C25: TV Player → Sync Agent → API | D25: Automatisé | E25: Batch quotidien | F25: Buffer local Pi | G25: Impressions en DB
A26: 6 | B26: Proof of broadcast | C26: Central Server | D26: Automatisé | E26: Temps réel | F26: Screenshot + timestamp | G26: Preuve certifiée SHA-256
A27: 7 | B27: Rapport annonceur | C27: Portail Annonceur / PDF | D27: Annonceur | E27: Self-service | F27: Stats agrégées | G27: PDF/Excel export
A29: DVS-1 — Neopro Platform (Development Value Stream)
A30: # | B30: Step | C30: Owner | D30: Outils | E30: Métriques | F30: Cadence
A31: 1 | B31: Product Discovery & Backlog | C31: PO (Gwenvael) | D31: SAFe Framework, Notion | E31: WSJF score, backlog depth | F31: Continu
A32: 2 | B32: Architecture & Design | C32: Tech Lead | D32: ADR, TypeScript strict | E32: Design reviews passés | F32: Par feature
A33: 3 | B33: Development (Sprint) | C33: Engineering | D33: Git, ESLint, Repository Pattern | E33: Vélocité SP/sprint, WIP | F33: Sprint 2 semaines
A34: 4 | B34: Testing & QA | C34: Engineering | D34: Jest, Karma, Playwright, Smoke | E34: 2 387 tests, coverage | F34: CI automatique
A35: 5 | B35: Release & OTA | C35: DevOps | D35: Git tags, Railway, FTP, Canary | E35: OTA success rate, rollback | F35: ~2 releases/semaine
A36: 6 | B36: Monitoring & Feedback | C36: Support | D36: Grafana, Prometheus, Slack | E36: Uptime, MTTR, NPS | F36: Continu
A38: Cartographie 12 Outils Neopro
A39: # | B39: Outil | C39: Type | D39: Public | E39: Protocole | F39: VS lié | G39: Features clés
A40: 1 | B40: Dashboard Admin | C40: Produit cloud | D40: Admin, Opérateurs | E40: HTTP + WebSocket | F40: OVS-1, OVS-2 | G40: Fleet mgmt, deploy, analytics, alerting, OTA
A41: 2 | B41: Portail Annonceur | C41: Produit cloud | D41: Annonceurs | E41: HTTP + JWT | F41: OVS-2 | G41: Upload pub, stats impressions, export PDF
A42: 3 | B42: Portail Agence | C42: Produit cloud | D42: Agences pub | E42: HTTP + JWT | F42: OVS-2 | G42: Multi-annonceurs, stats agrégées
A43: 4 | B43: Télécommande | C43: Produit cloud+edge | D43: Staff club | E43: Socket.IO | F43: OVS-1 | G43: Score, phases, timer, recording, vidéos
A44: 5 | B44: TV Player | C44: Produit edge | D44: Spectateurs | E44: Socket.IO local | F44: OVS-1, OVS-2 | G44: Double-buffer, overlay 6 sports, watermark
A45: 6 | B45: Admin Panel Pi | C45: Produit edge | D45: Staff + Tech | E45: HTTP local | F45: OVS-1 | G45: Club/Tech mode, upload local, debug
A46: 7 | B46: Central Server API | C46: Infra cloud | D46: Machines | E46: REST + WebSocket | F46: DVS-1 | G46: 21 repos, 9 handlers, rate limiting
A47: 8 | B47: Sync Agent | C47: Infra edge | D47: Système | E47: Socket.IO | F47: OVS-1, OVS-2 | G47: Config sync, video download, analytics batch
A48: 9 | B48: Pi Server Socket.IO | C48: Infra edge | D48: Télécommande, TV | E48: Socket.IO local | F48: OVS-1 | G48: 18 événements relay, score, phases
A49: 10 | B49: Watchdogs (4) | C49: Infra edge | D49: Système | E49: Bash + systemd | F49: DVS-1 | G49: Kiosk, sync-agent, network, hotspot
A50: 11 | B50: Monitoring | C50: Ops | D50: Support | E50: Prometheus + Grafana | F50: DVS-1 | G50: 30+ métriques, 18 seuils, 3 dashboards
A51: 12 | B51: Toolbox Déploiement | C51: Ops | D51: Techniciens | E51: Bash + SSH | F51: OVS-1 | G51: Golden image, setup, diagnostic, backup

Sheet Epics & LBC
A1: ← Dashboard
A3: Epic ID | B3: Name | C3: VS | D3: Theme | E3: WSJF | F3: PI | G3: Status | H3: Cost (SP) | I3: Benefit (€) | J3: Business Value | K3: Time Criticality | L3: Job Size
A4: E-01 | B4: Portail Sponsor Self-Service | C4: VS2 - Sponsor to Impression | D4: TS1 - Monétisation | E4: =(J4+K4)/L4 -> 13 | F4: PI-1 | G4: Backlog | H4: =SUMIF('Features & US'!A:A,A3,'Features & US'!E:E) -> 0 | I4: 50-100K€/an | J4: 5 | K4: 8 | L4: 1
A5: E-02 | B5: Rotation Sponsors | C5: VS2 - Sponsor to Impression | D5: TS1 - Monétisation | E5: =(J5+K5)/L5 -> 10 | F5: PI-1 | G5: Backlog | H5: =SUMIF('Features & US'!A:A,A1,'Features & US'!E:E) -> 0 | I5: 30-60K€/an | J5: 5 | K5: 5 | L5: 1
A6: E-03 | B6: Analytics Sponsors Avancé | C6: VS2 - Sponsor to Impression | D6: TS1 - Monétisation | E6: =(J6+K6)/L6 -> 21 | F6: PI-1 | G6: Backlog | H6: =SUMIF('Features & US'!A:A,A8,'Features & US'!E:E) -> 14 | I6: 20-40K€/an | J6: 8 | K6: 13 | L6: 1
A7: E-04 | B7: Profils Config Match | C7: VS1 - Club to Screen | D7: TS2 - Expérience Match | E7: =(J7+K7)/L7 -> 8 | F7: PI-1 | G7: Terminé | H7: =SUMIF('Features & US'!A:A,A4,'Features & US'!E:E) -> 19 | I7: Rétention +15% | J7: 3 | K7: 5 | L7: 1
A8: E-05 | B8: Motion Design Personnalisé | C8: VS2 - Sponsor to Impression | D8: TS2 - Expérience Match | E8: =(J8+K8)/L8 -> 5 | F8: PI-2 | G8: Backlog | H8: =SUMIF('Features & US'!A:A,A7,'Features & US'!E:E) -> 12 | I8: 15-30K€/an | J8: 5 | K8: 5 | L8: 2
A9: E-06 | B9: Onboarding Automatisé | C9: VS1 - Club to Screen | D9: TS3 - Acquisition | E9: =(J9+K9)/L9 -> 6.5 | F9: PI-1 | G9: Backlog | H9: =SUMIF('Features & US'!A:A,A6,'Features & US'!E:E) -> 13 | I9: -30% coût install. | J9: 5 | K9: 8 | L9: 2
A10: E-07 | B10: Résilience WiFi V2 | C10: VS1 - Club to Screen | D10: TS3 - Acquisition | E10: =(J10+K10)/L10 -> 10.5 | F10: PI-1 | G10: En cours | H10: =SUMIF('Features & US'!A:A,A12,'Features & US'!E:E) -> 20 | I10: -70% incidents WiFi | J10: 8 | K10: 13 | L10: 2
A11: E-08 | B11: Alertes Prédictives | C11: Transverse | D11: TS4 - Excellence Ops | E11: =(J11+K11)/L11 -> 13 | F11: PI-1 | G11: Terminé | H11: =SUMIF('Features & US'!A:A,A15,'Features & US'!E:E) -> 8 | I11: -50% MTTR | J11: 5 | K11: 8 | L11: 1
A12: E-09 | B12: Architecture Audit | C12: Transverse | D12: TS4 - Excellence Ops | E12: =(J12+K12)/L12 -> 5 | F12: PI-1 | G12: Terminé | H12: =SUMIF('Features & US'!A:A,A11,'Features & US'!E:E) -> 19 | I12: -40% dette tech | J12: 5 | K12: 5 | L12: 2
A13: E-10 | B13: Monitoring Fleet | C13: Transverse | D13: TS4 - Excellence Ops | E13: =(J13+K13)/L13 -> 10.5 | F13: PI-1 | G13: En cours | H13: =SUMIF('Features & US'!A:A,A17,'Features & US'!E:E) -> 6 | I13: -60% incidents ND | J13: 8 | K13: 13 | L13: 2
A14: E-11 | B14: Régie Publicitaire Régionale | C14: VS2 - Sponsor to Impression | D14: TS1 - Monétisation | E14: =(J14+K14)/L14 -> 4 | F14: PI-2 | G14: Backlog | H14: =SUMIF('Features & US'!A:A,A12,'Features & US'!E:E) -> 20 | I14: 100-200K€/an | J14: 3 | K14: 5 | L14: 2
A15: E-12 | B15: Multi-Écrans Synchronisés | C15: VS1 - Club to Screen | D15: TS2 - Expérience Match | E15: =(J15+K15)/L15 -> 2.5 | F15: PI-3 | G15: Backlog | H15: =SUMIF('Features & US'!A:A,A10,'Features & US'!E:E) -> 23 | I15: Upsell +30% | J15: 2 | K15: 3 | L15: 2
A16: E-13 | B16: Marque Blanche Club | C16: VS1 - Club to Screen | D16: TS2 - Expérience Match | E16: =(J16+K16)/L16 -> 4 | F16: PI-3 | G16: Backlog | H16: =SUMIF('Features & US'!A:A,A14,'Features & US'!E:E) -> 13 | I16: Upsell +20% | J16: 3 | K16: 5 | L16: 2
A17: E-14 | B17: Fonds de Solidarité Sport | C17: Transverse | D17: TS3 - Acquisition | E17: =(J17+K17)/L17 -> 4 | F17: PI-3 | G17: Backlog | H17: =SUMIF('Features & US'!A:A,A15,'Features & US'!E:E) -> 8 | I17: Image + 10 clubs | J17: 3 | K17: 5 | L17: 2
A18: E-15 | B18: Score en Live Phase 2 (API Fédérations) | C18: VS1 - Club to Screen | D18: TS2 - Expérience Match | E18: =(J18+K18)/L18 -> 8 | F18: PI-2 | G18: Backlog | H18: =SUMIF('Features & US'!A:A,A20,'Features & US'!E:E) -> 7 | I18: Engagement +25% | J18: 3 | K18: 5 | L18: 1
A19: E-16 | B19: Rapports Email Automatiques | C19: Transverse | D19: TS4 - Excellence Ops | E19: =(J19+K19)/L19 -> 3.5 | F19: PI-2 | G19: Backlog | H19: =SUMIF('Features & US'!A:A,A18,'Features & US'!E:E) -> 8 | I19: -80% temps rapports | J19: 2 | K19: 5 | L19: 2
A20: E-17 | B20: A/B Testing Créas Sponsors | C20: VS2 - Sponsor to Impression | D20: TS1 - Monétisation | E20: =(J20+K20)/L20 -> 5 | F20: PI-2 | G20: Backlog | H20: =SUMIF('Features & US'!A:A,A22,'Features & US'!E:E) -> 8 | I20: +15% conversion ads | J20: 2 | K20: 3 | L20: 1
A21: E-18 | B21: Intégrations Billetterie | C21: VS1 - Club to Screen | D21: TS2 - Expérience Match | E21: =(J21+K21)/L21 -> 5 | F21: PI-3 | G21: Backlog | H21: =SUMIF('Features & US'!A:A,A24,'Features & US'!E:E) -> 8 | I21: Revenue +10K€ | J21: 2 | K21: 3 | L21: 1
A22: E-19 | B22: Capteurs Présence Hardware | C22: VS1 - Club to Screen | D22: TS2 - Expérience Match | E22: =(J22+K22)/L22 -> 1.3333333 | F22: PI-3 | G22: Backlog | H22: =SUMIF('Features & US'!A:A,A20,'Features & US'!E:E) -> 7 | I22: Analytics premium | J22: 2 | K22: 2 | L22: 3
A23: E-20 | B23: Analytics Prédictives ML | C23: Transverse | D23: TS4 - Excellence Ops | E23: =(J23+K23)/L23 -> 5 | F23: PI-3 | G23: Backlog | H23: =SUMIF('Features & US'!A:A,A27,'Features & US'!E:E) -> 0 | I23: Churn -20% | J23: 2 | K23: 3 | L23: 1
A24: E-21 | B24: API Partenaires OAuth | C24: Transverse | D24: TS1 - Monétisation | E24: =(J24+K24)/L24 -> 5 | F24: PI-3 | G24: Backlog | H24: =SUMIF('Features & US'!A:A,A28,'Features & US'!E:E) -> 0 | I24: 5+ partenaires | J24: 2 | K24: 3 | L24: 1

Sheet Lean Business Cases
A1: ← Dashboard
A3: LEAN BUSINESS CASES — 21 Epics
A4: Epic ID | B4: Epic | C4: PI | D4: VS | E4: Thème | F4: WSJF | G4: Problème | H4: Solution | I4: Coût (SP) | J4: Bénéfice | K4: KPIs avancés | L4: Go/No-Go
A5: E-01 | B5: Portail Sponsor Self-Service | C5: PI-1 | D5: VS2 - Sponsor to Impression | E5: TS1 - Monétisation | F5: 13 | G5: Onboarding sponsor manuel (1-2 sem). Ne scale pas >10 sponsors. | H5: Portail self-service : compte, upload vidéo, sélection gymnases, validation admin. | I5: ='Epics & LBC'!H5 -> 0 | J5: Lead time 1-2 sem → <1 jour; support -60% | K5: Inscriptions self-service, taux complétion formulaire | L5: Go si ≥3 sponsors identifiés avant fin S1
A6: E-02 | B6: Rotation Sponsors | C6: PI-1 | D6: VS2 - Sponsor to Impression | E6: TS1 - Monétisation | F6: 10 | G6: Spots en boucle fixe. Aucune équité de rotation. Pas de preuve de diffusion. | H6: Algorithme rotation auto avec minimum garanti par match, pondération formule. | I6: ='Epics & LBC'!H9 -> 13 | J6: Taux renouvellement 40%→60%; argument commercial | K6: Passages/match/sponsor | L6: Go (dépendance bloquante E-03)
A7: E-03 | B7: Analytics Sponsors Avancé | C7: PI-1 | D7: VS2 - Sponsor to Impression | E7: TS1 - Monétisation | F7: 21 | G7: Aucun rapport de diffusion. Impossible prouver ROI. Frein acquisition sponsors. | H7: Dashboard analytics : impressions temps réel, heatmap, tendances, export PDF/CSV. | I7: ='Epics & LBC'!H4 -> 0 | J7: Renouvellement 60%→85%; reporting auto -100% manuel | K7: Consultation dashboard, rapports générés | L7: Go (WSJF max, critique VS2)
A8: E-04 | B8: Profils Config Match | C8: PI-1 | D8: VS1 - Club to Screen | E8: TS2 - Expérience Match | F8: 8 | G8: Config identique avant/pendant/après match. Changement manuel à chaque phase. | H8: Profils prédéfinis (Avant/Match/Mi-Temps/Après) avec transitions auto/manuelles. | I8: ='Epics & LBC'!H10 -> 20 | J8: NPS +10 pts; charge opérateur -80%/match | K8: Profils créés/club, taux utilisation transitions auto | L8: Go si ≥2 clubs demandent
A9: E-06 | B9: Onboarding Automatisé | C9: PI-1 | D9: VS1 - Club to Screen | E9: TS3 - Acquisition | F9: 6.5 | G9: Config SSH manuelle (2-3 jours/club). Bottleneck N°1 VS1. Ne scale pas >15 clubs. | H9: Wizard zero-touch : QR code → auto-registration → config → opérationnel en 30 min. | I9: ='Epics & LBC'!H11 -> 8 | J9: Lead time 2-3j → 30 min; capacité 1→5 clubs/sem | K9: Taux succès wizard, temps moyen onboarding | L9: Go (bottleneck critique, WSJF max)
A10: E-07 | B10: Résilience WiFi V2 | C10: PI-1 (reliquat) | D10: VS1 - Club to Screen | E10: TS3 - Acquisition | F10: 10.5 | G10: WiFi instable en gymnase. Déconnexions, fausses alertes. Source N°1 tickets support. | H10: Cache 48h, reconnexion agressive, monitoring signal, support clé USB WiFi externe. | I10: ='Epics & LBC'!H7 -> 19 | J10: Tickets WiFi -70%; uptime 95%→99% | K10: Taux reconnexion auto, durée déconnexion | L10: Go (dépendance E-06)
A11: E-08 | B11: Alertes Prédictives | C11: PI-1 (Done) | D11: Transverse | E11: TS4 - Excellence Ops | F11: 13 | G11: Alertes réactives uniquement. Aucune anticipation des pannes. | H11: Alertes prédictives : dégradation WiFi, espace disque, temp CPU, latence sync. | I11: ='Epics & LBC'!H6 -> 14 | J11: 60% pannes anticipées; MTTR 24h→2h | K11: Taux détection préventive, alertes déclenchées | L11: Go (améliore fiabilité perçue)
A12: E-09 | B12: Architecture Audit | C12: PI-1 (Done) | D12: Transverse | E12: TS4 - Excellence Ops | F12: 5 | G12: Controllers accèdent directement DB. Dette technique freinant le dev. | H12: Migration repository pattern, règles ESLint bloquantes, couverture tests +5%. | I12: ='Epics & LBC'!H12 -> 19 | J12: 100% controllers migrés; dev time -20% | K12: Controllers migrés, warnings ESLint restants | L12: Go (enabler technique, faible risque)
A13: E-10 | B13: Monitoring Fleet | C13: PI-1 (reliquat) | D13: Transverse | E13: TS4 - Excellence Ops | F13: 10.5 | G13: Monitoring basique. Pas de vue globale flotte. Ingérable >15 clubs. | H13: Dashboard flotte : carte Leaflet, statuts temps réel, métriques agrégées, tendances 30j. | I13: ='Epics & LBC'!H8 -> 12 | J13: Diagnostic 30min→5min; scalabilité 15→50+ clubs | K13: Taux adoption dashboard, fréquence consultation | L13: Go (indispensable scaling PI-2/PI-3)
A14: E-05 | B14: Motion Design Personnalisé | C14: PI-2 | D14: VS2 - Sponsor to Impression | E14: TS2 - Expérience Match | F14: 5 | G14: Animations statiques et identiques. Pas de personnalisation visuelle pour clubs Premium. | H14: Bibliothèque templates motion design personnalisables + upload animations custom Lottie/MP4. | I14: ='Epics & LBC'!H14 -> 20 | J14: Upsell +500€/an clubs Premium; différenciation | K14: Templates créés, taux adoption Premium | L14: Go si ≥5 clubs actifs fin PI-1
A15: E-11 | B15: Régie Publicitaire Régionale | C15: PI-2 | D15: VS2 - Sponsor to Impression | E15: TS1 - Monétisation | F15: 4 | G15: Seuls sponsors locaux peuvent diffuser. Pas de revenus passifs NEOPRO. | H15: Marketplace pubs : packs gymnases, ciblage géo, scheduling auto, reporting. Split 90/10. | I15: ='Epics & LBC'!H16 -> 13 | J15: Nouveau ARR régie; revenus passifs clubs | K15: Annonceurs inscrits, taux remplissage créneaux | L15: Go si ≥15 clubs actifs et E-01/02/03 terminés
A16: E-15 | B16: Score Live Phase 2 (API Fédérations) | C16: PI-2 | D16: VS1 - Club to Screen | E16: TS2 - Expérience Match | F16: 8 | G16: Score live nécessite saisie manuelle. Charge cognitive opérateur, risque erreur. | H16: Intégration API fédérations (FFHB, FFVB, FFBB) polling 30s + fallback manuel. | I16: ='Epics & LBC'!H13 -> 6 | J16: Saisie manuelle -100%; score plus fiable | K16: Matchs avec score auto, latence mise à jour | L16: Go si API FFHB accessible et ≥5 clubs handball
A17: E-16 | B17: Rapports Email Automatiques | C17: PI-2 | D17: Transverse | E17: TS4 - Excellence Ops | F17: 3.5 | G17: Rapports PDF existent mais doivent être téléchargés manuellement. Consultation 30%. | H17: Envoi auto rapport PDF mensuel par email. Liste diffusion configurable opt-in/opt-out. | I17: ='Epics & LBC'!H17 -> 8 | J17: Consultation 30%→80%; réduction churn | K17: Taux ouverture email, taux clics rapport | L17: Go (faible risque, fort impact)
A18: E-17 | B18: A/B Testing Créas Sponsors | C18: PI-2 | D18: VS2 - Sponsor to Impression | E18: TS1 - Monétisation | F18: 5 | G18: Un seul spot sans mesure d'efficacité. Décisions au feeling. | H18: Campagnes A/B : 2-3 variantes, allocation trafic, détermination statistique (χ²). | I18: ='Epics & LBC'!H15 -> 23 | J18: Upsell +600€/an/sponsor; complétion +10-15% | K18: Campagnes A/B créées, variantes testées | L18: Go si ≥5 sponsors actifs et E-02 livré
A19: E-12 | B19: Multi-Écrans Synchronisés | C19: PI-3 | D19: VS1 - Club to Screen | E19: TS2 - Expérience Match | F19: 2.5 | G19: Un seul écran par club. Gymnases multi-salles veulent 2-4 écrans synchronisés. | H19: Multi-Pi par site : master orchestre slaves via WebSocket local. | I19: ='Epics & LBC'!H23 -> 0 | J19: Upsell +600€/an/écran; pénétration semi-pro | K19: Clubs multi-écrans, latence synchronisation | L19: Go si ≥3 clubs demandent multi-écrans
A20: E-13 | B20: Marque Blanche Club | C20: PI-3 | D20: VS1 - Club to Screen | E20: TS2 - Expérience Match | F20: 4 | G20: Interface affiche branding NEOPRO. Clubs Premium veulent leurs couleurs/logo. | H20: Thématisation par club : logo, couleurs, police, écran accueil. 'Powered by NEOPRO' optionnel. | I20: ='Epics & LBC'!H21 -> 8 | J20: Argument Premium; NPS Premium +10 pts | K20: Taux activation marque blanche, thèmes créés | L20: Go si ≥5 clubs Premium actifs
A21: E-14 | B21: Fonds de Solidarité Sport | C21: PI-3 | D21: Transverse | E21: TS3 - Acquisition | F21: 4 | G21: Sport amateur manque de financement. Clubs modestes ne peuvent pas payer NEOPRO. | H21: Fonds alimenté par 1-2% revenus régie. Clubs éligibles reçoivent abonnement subventionné. | I21: ='Epics & LBC'!H22 -> 7 | J21: Impact RSE; couverture presse → acquisition | K21: Montant fonds, candidatures reçues | L21: Go si ARR régie >50K€
A22: E-18 | B22: Intégrations Billetterie | C22: PI-3 | D22: VS1 - Club to Screen | E22: TS2 - Expérience Match | F22: 5 | G22: Estimation audience manuelle et approximative. Sponsors veulent chiffres fiables. | H22: Intégration APIs billetterie (Weezevent, Eventbrite) → audience réelle dans analytics. | I22: ='Epics & LBC'!H18 -> 7 | J22: Données audience fiables; pipeline analytics auto | K22: Clubs connectés billetterie | L22: Go si ≥3 clubs utilisent Weezevent
A23: E-19 | B23: Capteurs Présence Hardware | C23: PI-3 | D23: VS1 - Club to Screen | E23: TS2 - Expérience Match | F23: 1.3 | G23: Clubs sans billetterie n'ont aucun moyen de compter spectateurs. | H23: Capteur infrarouge/caméra connecté au Pi. Comptage auto avec calibration initiale. | I23: ='Epics & LBC'!H24 -> 0 | J23: Audience 100% auto sans billetterie; upsell hardware | K23: Capteurs installés, précision comptage | L23: Go si ≥20 clubs actifs et ROI capteur validé
A24: E-20 | B24: Analytics Prédictives ML | C24: PI-3 | D24: Transverse | E24: TS4 - Excellence Ops | F24: 5 | G24: Pas de prédiction engagement club ni recommandations automatiques. | H24: ML time-series : engagement futur, anomalies, recommandations actionables. | I24: ='Epics & LBC'!H19 -> 8 | J24: Churn proactif réduit; engagement +20% | K24: Précision modèle, recommandations générées | L24: Go si ≥15 clubs avec 6 mois historique
A25: E-21 | B25: API Partenaires OAuth | C25: PI-3 | D25: Transverse | E25: TS1 - Monétisation | F25: 5 | G25: Partenaires n'ont pas d'accès programmatique. Tout via dashboard/exports manuels. | H25: API REST OAuth 2.0 avec scopes, rate limiting, portail développeurs. | I25: ='Epics & LBC'!H20 -> 8 | J25: Nouveau ARR API; écosystème partenaires | K25: Clients API, requêtes/jour | L25: Go si ≥3 partenaires demandent accès API
A28: RÉSUMÉ
A29: PI | B29: Epics
A30: PI-1 | B30: =COUNTIF(C5:C25,"PI-1*") -> 9
A31: PI-2 | B31: =COUNTIF(C5:C25,"PI-2*") -> 5
A32: PI-3 | B32: =COUNTIF(C5:C25,"PI-3*") -> 7
A33: Total | B33: =COUNTA(A5:A25) -> 21

Sheet Features & US
A1: ← Dashboard
A3: FEATURE BACKLOG
A4: Epic | B4: Feature ID | C4: Feature | D4: US Count | E4: SP | F4: Priority | G4: Statut | H4: Notes | I4: PI | J4: Sprint
A5: E-01 | B5: F-01.1 | C5: Inscription et profil sponsor | D5: =COUNTIF('User Stories'!B:B,B5) -> 3 | E5: =SUMIF('User Stories'!B:B,B5,'User Stories'!E:E) -> 7 | F5: 1 | G5: Backlog | I5: PI-1 (Fév-Mar 2026) | J5: S3
A6: E-01 | B6: F-01.2 | C6: Upload vidéo sponsor | D6: =COUNTIF('User Stories'!B:B,B6) -> 3 | E6: =SUMIF('User Stories'!B:B,B6,'User Stories'!E:E) -> 7 | F6: 1 | G6: Backlog | I6: PI-1 (Fév-Mar 2026) | J6: S2
A7: E-01 | B7: F-01.3 | C7: Validation admin des spots | D7: =COUNTIF('User Stories'!B:B,B7) -> 2 | E7: =SUMIF('User Stories'!B:B,B7,'User Stories'!E:E) -> 5 | F7: 1 | G7: Backlog | I7: PI-1 (Fév-Mar 2026) | J7: S2
A8: E-02 | B8: F-02.1 | C8: Algorithme de rotation équitable | D8: =COUNTIF('User Stories'!B:B,B8) -> 2 | E8: =SUMIF('User Stories'!B:B,B8,'User Stories'!E:E) -> 8 | F8: 1 | G8: Backlog | I8: PI-1 (Fév-Mar 2026) | J8: S2
A9: E-03 | B9: F-03.1 | C9: Dashboard impressions sponsor | D9: =COUNTIF('User Stories'!B:B,B9) -> 2 | E9: =SUMIF('User Stories'!B:B,B9,'User Stories'!E:E) -> 5 | F9: 1 | G9: Backlog | I9: PI-1 (Fév-Mar 2026) | J9: S3
A10: E-03 | B10: F-03.2 | C10: Export rapport PDF/CSV | D10: =COUNTIF('User Stories'!B:B,B10) -> 2 | E10: =SUMIF('User Stories'!B:B,B10,'User Stories'!E:E) -> 3 | F10: 1 | G10: Backlog | I10: PI-1 (Fév-Mar 2026) | J10: S3
A11: E-04 | B11: F-04.1 | C11: Création de profils prédéfinis | D11: =COUNTIF('User Stories'!B:B,B11) -> 3 | E11: =SUMIF('User Stories'!B:B,B11,'User Stories'!E:E) -> 7 | F11: 1 | G11: Terminé | I11: PI-1 (Fév-Mar 2026) | J11: S2
A12: E-04 | B12: F-04.2 | C12: Switch depuis la télécommande | D12: =COUNTIF('User Stories'!B:B,B12) -> 2 | E12: =SUMIF('User Stories'!B:B,B12,'User Stories'!E:E) -> 5 | F12: 1 | G12: Terminé | I12: PI-1 (Fév-Mar 2026) | J12: S3
A13: E-05 | B13: F-05.1 | C13: Bibliothèque de templates motion design | D13: =COUNTIF('User Stories'!B:B,B13) -> 2 | E13: =SUMIF('User Stories'!B:B,B13,'User Stories'!E:E) -> 8 | F13: 1 | G13: Backlog | I13: PI-2 (Avr-Mai 2026) | J13: S6
A14: E-06 | B14: F-06.1 | C14: Auto-provisioning Pi | D14: =COUNTIF('User Stories'!B:B,B14) -> 3 | E14: =SUMIF('User Stories'!B:B,B14,'User Stories'!E:E) -> 12 | F14: 1 | G14: Backlog | I14: PI-1 (Fév-Mar 2026) | J14: S2
A15: E-06 | B15: F-06.2 | C15: Wizard de configuration club | D15: =COUNTIF('User Stories'!B:B,B15) -> 2 | E15: =SUMIF('User Stories'!B:B,B15,'User Stories'!E:E) -> 5 | F15: 1 | G15: Backlog | I15: PI-1 (Fév-Mar 2026) | J15: S3
A16: E-07 | B16: F-07.1 | C16: Cache local étendu (48h) | D16: =COUNTIF('User Stories'!B:B,B16) -> 3 | E16: =SUMIF('User Stories'!B:B,B16,'User Stories'!E:E) -> 10 | F16: 1 | G16: Terminé | I16: PI-1 (Fév-Mar 2026) | J16: S3
... A28: E-16 | B28: F-16.1 | C28: Envoi automatique mensuel | D28: =COUNTIF('User Stories'!B:B,B28) -> 2 | E28: =SUMIF('User Stories'!B:B,B28,'User Stories'!E:E) -> 4 | F28: 1 | G28: Backlog | I28: PI-2 (Avr-Mai 2026) | J28: S6
A29: E-02 | B29: F-02.2 | C29: Configuration rotation par gymnase | D29: =COUNTIF('User Stories'!B:B,B29) -> 2 | E29: =SUMIF('User Stories'!B:B,B29,'User Stories'!E:E) -> 5 | F29: 2 | G29: Backlog | I29: PI-2 (Avr-Mai 2026)
A30: E-03 | B30: F-03.3 | C30: Heatmap de diffusion | D30: =COUNTIF('User Stories'!B:B,B30) -> 2 | E30: =SUMIF('User Stories'!B:B,B30,'User Stories'!E:E) -> 5 | F30: 2 | G30: Backlog | I30: PI-2 (Avr-Mai 2026)
A31: E-05 | B31: F-05.2 | C31: Upload d'animations custom (Lottie/MP4) | D31: =COUNTIF('User Stories'!B:B,B31) -> 2 | E31: =SUMIF('User Stories'!B:B,B31,'User Stories'!E:E) -> 6 | F31: 2 | G31: Backlog | I31: PI-2 (Avr-Mai 2026)
A32: E-07 | B32: F-07.3 | C32: Support clé USB WiFi externe | D32: =COUNTIF('User Stories'!B:B,B32) -> 2 | E32: =SUMIF('User Stories'!B:B,B32,'User Stories'!E:E) -> 5 | F32: 2 | G32: Backlog | I32: PI-2 (Avr-Mai 2026)
A33: E-14 | B33: F-14.1 | C33: Gestion du fonds | D33: =COUNTIF('User Stories'!B:B,B33) -> 2 | E33: =SUMIF('User Stories'!B:B,B33,'User Stories'!E:E) -> 6 | F33: 2 | G33: Backlog | I33: PI-3 (Juin-Juil 2026)
A34: E-15 | B34: F-15.1 | C34: Intégration API fédérations sportives | D34: =COUNTIF('User Stories'!B:B,B34) -> 2 | E34: =SUMIF('User Stories'!B:B,B34,'User Stories'!E:E) -> 8 | F34: 2 | G34: Backlog | I34: PI-2 (Avr-Mai 2026)
A35: E-17 | B35: F-17.1 | C35: Campagnes A/B Test | D35: =COUNTIF('User Stories'!B:B,B35) -> 2 | E35: =SUMIF('User Stories'!B:B,B35,'User Stories'!E:E) -> 7 | F35: 2 | G35: Backlog | I35: PI-2 (Avr-Mai 2026)
A36: E-18 | B36: F-18.1 | C36: Audience réelle via billetterie | D36: =COUNTIF('User Stories'!B:B,B36) -> 2 | E36: =SUMIF('User Stories'!B:B,B36,'User Stories'!E:E) -> 8 | F36: 2 | G36: Backlog | I36: PI-3 (Juin-Juil 2026)
A37: E-19 | B37: F-19.1 | C37: Comptage spectateurs automatique | D37: =COUNTIF('User Stories'!B:B,B37) -> 2 | E37: =SUMIF('User Stories'!B:B,B37,'User Stories'!E:E) -> 8 | F37: 3 | G37: Backlog | I37: PI-3 (Juin-Juil 2026)
A38: E-20 | B38: F-20.1 | C38: Prédictions engagement et uptime | D38: =COUNTIF('User Stories'!B:B,B38) -> 2 | E38: =SUMIF('User Stories'!B:B,B38,'User Stories'!E:E) -> 8 | F38: 3 | G38: Backlog | I38: PI-3 (Juin-Juil 2026)
A39: E-21 | B39: F-21.1 | C39: API OAuth 2.0 pour partenaires | D39: =COUNTIF('User Stories'!B:B,B39) -> 2 | E39: =SUMIF('User Stories'!B:B,B39,'User Stories'!E:E) -> 8 | F39: 3 | G39: Backlog | I39: PI-3 (Juin-Juil 2026)
A41: SUMMARY
A42: PI | B42: Features | C42: Total SP | D42: Terminé | E42: Backlog
A43: PI-1 (Fév-Mar 2026) | B43: =COUNTIF(I5:I39,"PI-1*") -> 18 | C43: =SUMIF(I5:I39,"PI-1*",E5:E39) -> 134 | D43: =COUNTIFS(I5:I39,"PI-1*",G5:G39,"Terminé") -> 9 | E43: =COUNTIFS(I5:I39,"PI-1*",G5:G39,"Backlog") -> 9
A44: PI-2 (Avr-Mai 2026) | B44: =COUNTIF(I5:I39,"PI-2*") -> 10 | C44: =SUMIF(I5:I39,"PI-2*",E5:E39) -> 61 | D44: =COUNTIFS(I5:I39,"PI-2*",G5:G39,"Terminé") -> 0 | E44: =COUNTIFS(I5:I39,"PI-2*",G5:G39,"Backlog") -> 10
A45: PI-3 (Juin-Juil 2026) | B45: =COUNTIF(I5:I39,"PI-3*") -> 7 | C45: =SUMIF(I5:I39,"PI-3*",E5:E39) -> 51 | D45: =COUNTIFS(I5:I39,"PI-3*",G5:G39,"Terminé") -> 0 | E45: =COUNTIFS(I5:I39,"PI-3*",G5:G39,"Backlog") -> 7

Sheet User Stories
A1: ← Dashboard | B1: ← Features & US
A3: USER STORIES — 250 US (76 planifiées + 174 livrées)
A4: US ID | B4: Feature ID | C4: Epic ID | D4: User Story | E4: SP | F4: Statut | G4: Sprint | H4: Critères d'acceptation | I4: Domaine | J4: Catégorie
A5: US-01.1.1 | B5: F-01.1 | C5: E-01 | D5: En tant qu'annonceur, je veux créer un compte et un profil complet afin de pouvoir proposer mes spots publicitaires | E5: 3 | F5: Backlog | G5: S3 | H5: • Formulaire d'inscription avec validation • Champs : nom, email, téléphone, secteur d'activité, budget • Vérification d'email • Conditions générales à accepter | I5: Sponsors & Monétisation | J5: Planifié
A6: US-01.1.2 | B6: F-01.1 | C6: E-01 | D6: En tant qu'annonceur, je veux gérer mon profil et mettre à jour mes informations afin de maintenir mes coordonnées à jour | E6: 2 | F6: Backlog | G6: S3 | H6: • Page de profil modifiable • Changement de mot de passe • Préférences de notification • Suppression de compte (soft delete) | I6: Sponsors & Monétisation | J6: Planifié
A7: US-01.1.3 | B7: F-01.1 | C7: E-01 | D7: En tant qu'administrateur NEOPRO, je veux valider les profils sponsors afin de garantir la qualité des annonceurs | E7: 2 | F7: Backlog | G7: S3 | H7: • Liste d'attente des sponsors non vérifiés • Actions : valider, rejeter (avec raison) • Notifications au sponsor • Audit trail des validations | I7: Sponsors & Monétisation | J7: Planifié
A8: US-01.2.1 | B8: F-01.2 | C8: E-01 | D8: En tant qu'annonceur, je veux uploader une vidéo publicitaire afin de la proposer aux clubs | E8: 3 | F8: Backlog | G8: S2 | H8: • Interface d'upload drag-and-drop • Formats acceptés : MP4, WebM • Taille max : 500 MB • Durée : 30s à 2min • Barre de progression de l'upload • Conversion automatique en HLS | I8: Sponsors & Monétisation | J8: Planifié
A9: US-01.2.2 | B9: F-01.2 | C9: E-01 | D9: En tant qu'annonceur, je veux ajouter des métadonnées à ma vidéo afin de la rendre découvrable | E9: 2 | F9: Backlog | G9: S2 | H9: • Champs : titre, description, catégorie, tags • Logo de la marque • URL de destination (CTR) • Durée de validité du spot | I9: Sponsors & Monétisation | J9: Planifié
A10: US-01.2.3 | B10: F-01.2 | C10: E-01 | D10: En tant qu'administrateur NEOPRO, je veux approuver les vidéos avant diffusion afin de respecter la charte | E10: 2 | F10: Backlog | G10: S2 | H10: • Interface de modération avec preview vidéo • Actions : approuver, rejeter (raison) • Vérification du contenu inadapté • Historique des approuvations | I10: Sponsors & Monétisation | J10: Planifié
A11: US-01.3.1 | B11: F-01.3 | C11: E-01 | D11: En tant qu'administrateur NEOPRO, je veux valider les spots avant mise en production afin d'assurer la qualité de contenu | E11: 3 | F11: Backlog | G11: S2 | H11: • Checklist de validation (format, durée, contenu) • Preview haute résolution • Test de lecture sur les différents profils Pi • Signature numérique de l'approbation | I11: Sponsors & Monétisation | J11: Planifié
A12: US-01.3.2 | B12: F-01.3 | C12: E-01 | D12: En tant qu'opérateur, je veux consulter les spots approuvés et les sélectionner pour mon club afin de monétiser la TV | E12: 2 | F12: Backlog | G12: S2 | H12: • Catalogue des spots validés • Filtres : catégorie, durée, secteur • Sélection multiple • Aperçu avant activation | I12: Sponsors & Monétisation | J12: Planifié
A13: US-02.1.1 | B13: F-02.1 | C13: E-02 | D13: En tant qu'opérateur, je veux que les vidéos publicitaires soient diffusées de manière équitable afin de respecter les contrats sponsors | E13: 5 | F13: Backlog | G13: S2 | H13: • Algorithme de round-robin basé sur le poids (budget) • Limite : max 20% du temps d'antenne pour un sponsor • Respect des plages horaires personnalisées • Équité sur une fenêtre glissante de 24h | I13: Sponsors & Monétisation | J13: Planifié
A14: US-02.1.2 | B14: F-02.1 | C14: E-02 | D14: En tant qu'administrateur NEOPRO, je veux monitorer la rotation afin de vérifier l'équité | E14: 3 | F14: Backlog | G14: S2 | H14: • Dashboard de temps d'antenne par sponsor • Alertes si déséquilibre > 5% • Rapport mensuel de conformité • Ajustement manuel possible | I14: Sponsors & Monétisation | J14: Planifié
A15: US-02.2.1 | B15: F-02.2 | C15: E-02 | D15: En tant qu'opérateur, je veux configurer la rotation des vidéos différemment par gymnase afin d'adapter à chaque espace | E15: 3 | F15: Backlog | H15: • Association clubs/gymnases à des Pi distincts • Profils de rotation spécifiques par gymnase • Horaires décalés par zone • Vue d'ensemble de la rotation globale | I15: Sponsors & Monétisation | J15: Planifié
A16: US-02.2.2 | B16: F-02.2 | C16: E-02 | D16: En tant qu'administrateur NEOPRO, je veux valider les configurations par gymnase afin d'éviter les conflits | E16: 2 | F16: Backlog | H16: • Vérification d'intégrité des configs • Alertes en cas de chevauchement • Simulation avant activation • Historique des configurations | I16: Sponsors & Monétisation | J16: Planifié
A17: US-03.1.1 | B17: F-03.1 | C17: E-03 | D17: En tant qu'annonceur, je veux voir les métriques de mes vidéos afin d'évaluer le ROI de ma campagne | E17: 3 | F17: Backlog | G17: S3 | H17: • Nombre d'impressions par vidéo • Nombre de clubs diffusant mon spot • Durée moyenne de visionnage • Graphiques par jour/semaine/mois | I17: Sponsors & Monétisation | J17: Planifié
A18: US-03.1.2 | B18: F-03.1 | C18: E-03 | D18: En tant qu'annonceur, je veux tracker les clics sur mon URL afin de mesurer la conversion | E18: 2 | F18: Backlog | G18: S3 | H18: • Nombre de clics par vidéo • Taux de CTR (%) • Géolocalisation des clics • Intégration UTM optionnelle | I18: Sponsors & Monétisation | J18: Planifié
A19: US-03.2.1 | B19: F-03.2 | C19: E-03 | D19: En tant qu'annonceur, je veux exporter mes rapports en PDF pour les présenter à mon agence afin de prouver le ROI | E19: 2 | F19: Backlog | G19: S3 | H19: • Export PDF avec logo de la marque • Résumé exécutif • Graphiques professionnels • Date de génération et signature | I19: Sponsors & Monétisation | J19: Planifié
A20: US-03.2.2 | B20: F-03.2 | C20: E-03 | D20: En tant qu'annonceur, je veux exporter les données en CSV pour les analyser dans Excel afin de faire des analyses détaillées | E20: 1 | F20: Backlog | G20: S3 | H20: • Export CSV des impressions brutes • Format UTF-8 avec BOM • Colonnes : date, club, durée, région • Tri par colonne | I20: Sponsors & Monétisation | J20: Planifié
A21: US-03.3.1 | B21: F-03.3 | C21: E-03 | D21: En tant qu'annonceur, je veux voir où ma vidéo est la plus diffusée géographiquement afin d'optimiser mon investissement | E21: 3 | F21: Backlog | H21: • Heatmap par région/département • Intensité basée sur nombre d'impressions • Filtres : période, sport, type club • Export de la heatmap | I21: Sponsors & Monétisation | J21: Planifié
A22: US-03.3.2 | B22: F-03.3 | C22: E-03 | D22: En tant qu'administrateur NEOPRO, je veux analyser la couverture de la flotte afin d'identifier les zones blanches | E22: 2 | F22: Backlog | H22: • Heatmap d'uptime par région • Zones de faible couverture identifiées • Recommandations d'expansion | I22: Sponsors & Monétisation | J22: Planifié
A23: US-04.1.1 | B23: F-04.1 | C23: E-04 | D23: En tant qu'opérateur, je veux créer des profils de match prédéfinis pour différents sports afin de gagner du temps lors de la configuration initiale | E23: 3 | F23: Terminé | G23: S2 | H23: • Interface de création de profils accessibles depuis le dashboard • Possibilité de sauvegarder les paramètres (résolution, FPS, durée) • Validation des valeurs de configuration • Confirmation avant sauvegarde | I23: Expérience Match | J23: Planifié
A24: US-04.1.2 | B24: F-04.1 | C24: E-04 | D24: En tant qu'administrateur NEOPRO, je veux pouvoir modifier les profils prédéfinis globalement afin de standardiser les configurations pour la flotte | E24: 2 | F24: Terminé | G24: S2 | H24: • Accès admin aux modèles de profils • Historique des modifications • Notification aux opérateurs des changements | I24: Expérience Match | J24: Planifié
A25: US-04.1.3 | B25: F-04.1 | C25: E-04 | D25: En tant que bénévole du club, je veux appliquer un profil prédéfini à un match afin de lancer rapidement la retransmission | E25: 2 | F25: Terminé | G25: S2 | H25: • Boutons de sélection rapide des profils sur la TV • Affichage du profil appliqué • Possibilité de revenir en arrière | I25: Expérience Match | J25: Planifié
A26: US-04.2.1 | B26: F-04.2 | C26: E-04 | D26: En tant que bénévole du club, je veux changer les profils de match depuis ma télécommande afin de contrôler l'affichage sans accès au Pi | E26: 3 | F26: Terminé | G26: S3 | H26: • Boutons dédiés sur la télécommande Socket.IO pour changer de profil • Confirmation visuelle du changement sur l'écran • Latence < 500ms • Feedback audio/visuel du changement | I26: Expérience Match | J26: Planifié
A27: US-04.2.2 | B27: F-04.2 | C27: E-04 | D27: En tant qu'opérateur, je veux limiter les profils accessibles depuis la télécommande afin de prévenir les mauvaises manipulations | E27: 2 | F27: Terminé | G27: S3 | H27: • Configuration des profils autorisés par club • Verrouillage des profils non autorisés • Audit des changements de profil | I27: Expérience Match | J27: Planifié
A28: US-05.1.1 | B28: F-05.1 | C28: E-05 | D28: En tant qu'annonceur, je veux utiliser des templates motion design prédéfinis afin de créer rapidement des vidéos professionnelles | E28: 5 | F28: Backlog | G28: S3 | H28: • Bibliothèque de 20+ templates (intro, outro, transition) • Catégories : sport, retail, services, F&B • Personnalisation : couleurs, texte, logo • Export en MP4 HQ | I28: Expérience Match | J28: Planifié
A29: US-05.1.2 | B29: F-05.1 | C29: E-05 | D29: En tant qu'agence, je veux créer et gérer mes templates custom afin de maintenir la cohérence de marque de mes clients | E29: 3 | F29: Backlog | G29: S3 | H29: • Création de templates (upload source) • Versioning des templates • Partage entre collaborateurs • Branding guidelines par template | I29: Expérience Match | J29: Planifié
A30: US-05.2.1 | B30: F-05.2 | C30: E-05 | D30: En tant qu'annonceur, je veux uploader des animations Lottie ou MP4 personnalisées afin d'avoir une totale liberté créative | E30: 3 | F30: Backlog | H30: • Support des fichiers Lottie (.json) • Support MP4 avec codec H.264 • Taille max 100 MB • Validation de la structure du fichier • Preview avant livraison | I30: Expérience Match | J30: Planifié
A31: US-05.2.2 | B31: F-05.2 | C31: E-05 | D31: En tant que développeur, je veux supporter les animations Lottie sur les Pi afin d'enrichir les capacités créatives | E31: 3 | F31: Backlog | H31: • Intégration lottie-web • Optimisation de la performance • Fallback si format non supporté • Tests de rendu sur différents Pi | I31: Expérience Match | J31: Planifié
A32: US-06.1.1 | B32: F-06.1 | C32: E-06 | D32: En tant qu'opérateur, je veux que mon Raspberry Pi se configure automatiquement afin de réduire le temps d'installation | E32: 5 | F32: Backlog | G32: S2 | H32: • Image Raspbian pré-configurée • Téléchargement auto de l'agent Neopro • Configuration réseau automatique (WiFi/Ethernet) • Pairing avec le dashboard via QR code • Tests de connectivité avant fin du provisioning | I32: Onboarding & Déploiement | J32: Planifié
A33: US-06.1.2 | B33: F-06.1 | C33: E-06 | D33: En tant qu'administrateur NEOPRO, je veux générer des codes de pairing uniques afin de sécuriser l'onboarding | E33: 2 | F33: Backlog | G33: S2 | H33: • Génération de codes aléatoires (6 caractères) • Expiration après 24h ou après utilisation • Audit trail des pairings • Blocage après 3 tentatives échouées | I33: Onboarding & Déploiement | J33: Planifié
A34: US-06.2.1 | B34: F-06.2 | C34: E-06 | D34: En tant qu'opérateur, je veux suivre un wizard pour configurer mon club afin de démarrer rapidement sans formation | E34: 3 | F34: Backlog | G34: S3 | H34: • Étapes : infos club, sélection spots, configuration TV, test • Tooltips d'aide à chaque étape • Sauvegarde des brouillons • Envoi de résumé par email | I34: Onboarding & Déploiement | J34: Planifié
A35: US-06.2.2 | B35: F-06.2 | C35: E-06 | D35: En tant qu'administrateur NEOPRO, je veux tracker les clubs incomplets afin de relancer les opérateurs | E35: 2 | F35: Backlog | G35: S3 | H35: • Statut : setup en cours, complet, inactif • Rappels automatiques après 7 jours • Rapport de configuration par région | I35: Onboarding & Déploiement | J35: Planifié
A36: US-07.1.1 | B36: F-07.1 | C36: E-07 | D36: En tant que bénévole du club, je veux que le Raspberry Pi garde en cache les vidéos et contenus pendant 48h afin de pouvoir les diffuser même si la connexion WiFi est coupée | E36: 5 | F36: Terminé | G36: S1 | H36: • Cache sur le disque local du Pi avec durée de 48h • Gestion intelligente de l'espace disque (suppression FIFO) • Synchronisation automatique lors du retour de connexion • Priorité à la mise en cache des vidéos les plus regardées | I36: Résilience & Edge | J36: Planifié
A37: US-07.1.2 | B37: F-07.1 | C37: E-07 | D37: En tant qu'opérateur, je veux monitorer l'état du cache afin de vérifier la continuité de service | E37: 2 | F37: Terminé | G37: S1 | H37: • Endpoint API pour consulter l'état du cache • Dashboard affichant le statut du cache par Pi • Alertes si le cache est plein ou corrompu | I37: Résilience & Edge | J37: Planifié
A38: US-07.1.3 | B38: F-07.1 | C38: E-07 | D38: En tant que développeur, je veux implémenter un mécanisme de cache robuste afin d'assurer la résilience hors ligne | E38: 3 | F38: Terminé | G38: S1 | H38: • Compression des contenus en cache • Vérification d'intégrité des fichiers cachés • Logs de cache-hit/cache-miss • Tests unitaires du cache | I38: Résilience & Edge | J38: Planifié
A39: US-07.2.1 | B39: F-07.2 | C39: E-07 | D39: En tant qu'opérateur, je veux visualiser la force du signal WiFi de chaque Pi afin de diagnostiquer les problèmes de connectivité | E39: 3 | F39: Terminé | G39: S2 | H39: • Mesure en dBm du signal WiFi toutes les 30 secondes • Stockage des mesures sur 7 jours • Affichage graphique (courbe) sur le dashboard • Seuils d'alerte (< -70 dBm = warning, < -80 dBm = critical) | I39: Résilience & Edge | J39: Planifié
A40: US-07.2.2 | B40: F-07.2 | C40: E-07 | D40: En tant que développeur, je veux instrumenter le daemon Pi pour rapporter les métriques WiFi afin de faciliter le diagnostic | E40: 3 | F40: Terminé | G40: S2 | H40: • Script de monitoring WiFi sur le Raspberry Pi • Endpoint d'exposition des métriques (Prometheus) • Tests de robustesse du monitoring • Documentation du setup | I40: Résilience & Edge | J40: Planifié
A41: US-07.2.3 | B41: F-07.2 | C41: E-07 | D41: En tant qu'administrateur NEOPRO, je veux recevoir des alertes si un Pi perd sa connexion afin d'intervenir rapidement | E41: 2 | F41: Terminé | G41: S2 | H41: • Règles d'alertes basées sur le signal WiFi • Notifications push/email si signal < seuil • Historique des incidents | I41: Résilience & Edge | J41: Planifié
A42: US-07.3.1 | B42: F-07.3 | C42: E-07 | D42: En tant qu'opérateur, je veux utiliser une clé USB WiFi externe afin d'améliorer la réception dans les zones difficiles | E42: 3 | F42: Backlog | H42: • Support des clés USB (RTL8812AU, RTL8821AU) • Configuration automatique via firmware • Fallback sur WiFi intégré en cas d'échec • Monitoring de la clé USB (température, signal) | I42: Résilience & Edge | J42: Planifié
A43: US-07.3.2 | B43: F-07.3 | C43: E-07 | D43: En tant qu'administrateur NEOPRO, je veux gérer le parc de clés USB afin de supporter l'expansion | E43: 2 | F43: Backlog | H43: • Inventaire des clés par site • Alertes de dysfonctionnement • Recommandations de remplacement • Documentation de setup | I43: Résilience & Edge | J43: Planifié
A44: US-08.1.1 | B44: F-08.1 | C44: E-08 | D44: En tant qu'opérateur, je veux créer des règles d'alertes prédictives afin d'anticiper les problèmes de performance | E44: 5 | F44: Terminé | G44: S2 | H44: • Interface de création de règles avec conditions logiques • Métriques disponibles : CPU, mémoire, uptime, signal WiFi • Actions d'alerte : email, SMS, dashboard • Simulation des règles avant activation | I44: Monitoring & Infrastructure | J44: Planifié
A45: US-08.1.2 | B45: F-08.1 | C45: E-08 | D45: En tant qu'administrateur NEOPRO, je veux automatiser la escalade des alertes afin de ne pas surcharger les opérateurs | E45: 3 | F45: Terminé | G45: S2 | H45: • Escalade progressives (warning → critical) • Silence temporaire des alertes après action • Agrégation des alertes similaires • Rapports de synthèse hebdomadaires | I45: Monitoring & Infrastructure | J45: Planifié
A46: US-08.2.1 | B46: F-08.2 | C46: E-08 | D46: En tant qu'opérateur, je veux visualiser les tendances de performance de mes clubs afin d'identifier les problèmes récurrents | E46: 5 | F46: Terminé | G46: S3 | H46: • Graphiques multi-axes : CPU, mémoire, uptime par club • Filtres par période (7j, 30j, 90j) • Export des tendances en CSV • Comparaison inter-clubs (peer benchmarking) | I46: Monitoring & Infrastructure | J46: Planifié
A47: US-08.2.2 | B47: F-08.2 | C47: E-08 | D47: En tant qu'administrateur NEOPRO, je veux analyser les tendances de la flotte afin d'optimiser les capacités | E47: 3 | F47: Terminé | G47: S3 | H47: • Dashboard agrégé pour tous les sites • Identification des Pi surloadés ou sous-utilisés • Recommandations d'optimisation • Accès en temps réel | I47: Monitoring & Infrastructure | J47: Planifié
A48: US-08.2.3 | B48: F-08.2 | C48: E-08 | D48: En tant que développeur, je veux stocker les métriques historiques afin de supporter l'analyse des tendances | E48: 3 | F48: Terminé | G48: S3 | H48: • Retention des métriques sur 365 jours • Requêtes d'agrégation performantes • Index sur les colonnes temporelles • Archivage automatique | I48: Monitoring & Infrastructure | J48: Planifié
A49: US-09.1.1 | B49: F-09.1 | C49: E-09 | D49: En tant que développeur, je veux refactoriser les controllers API afin de respecter le pattern repository et améliorer la testabilité | E49: 8 | F49: Terminé | G49: S1 | H49: • Création de repositories pour chaque entité (Site, Video, User, etc.) • Remplacement des query() directs par les repositories • Tests unitaires des repositories • Documentation du pattern dans le README | I49: Architecture & Qualité | J49: Planifié
A50: US-09.1.2 | B50: F-09.1 | C50: E-09 | D50: En tant que développeur, je veux ajouter une règle ESLint pour bloquer les query() directs afin d'éviter les régressions | E50: 2 | F50: Terminé | G50: S1 | H50: • Règle ESLint custom qui bloque query() hors repositories • CI/CD vérifie la règle • Message d'erreur clair pour les développeurs | I50: Architecture & Qualité | J50: Planifié
A51: US-09.2.1 | B51: F-09.2 | C51: E-09 | D51: En tant qu'administrateur NEOPRO, je veux un audit complet de sécurité afin de valider la conformité OWASP | E51: 5 | F51: Terminé | G51: S1 | H51: • Test OWASP Top 10 (injection, XSS, CSRF, etc.) • Scan des dépendances (npm audit) • Rapport avec recommandations • Plan d'action pour les vulnérabilités | I51: Architecture & Qualité | J51: Planifié
A52: US-09.2.2 | B52: F-09.2 | C52: E-09 | D52: En tant que développeur, je veux optimiser les performances de l'API afin de réduire la latence | E52: 5 | F52: Terminé | G52: S1 | H52: • Profiling des requêtes les plus lentes • Ajout d'indexes manquants • Optimisation des joins • Benchmarks avant/après avec résultats documentés | I52: Architecture & Qualité | J52: Planifié
A53: US-10.1.1 | B53: F-10.1 | C53: E-10 | D53: En tant qu'administrateur NEOPRO, je veux visualiser la géolocalisation de tous les clubs sur une carte afin de gérer la flotte spatialement | E53: 3 | F53: Backlog | G53: S3 | H53: • Carte Leaflet/OpenStreetMap • Marqueurs par site avec status (online/offline) • Clustering pour les zones denses • Info popup : nom, ville, nb spectateurs | I53: Monitoring & Infrastructure | J53: Planifié
A54: US-10.1.2 | B54: F-10.1 | C54: E-10 | D54: En tant qu'opérateur régional, je veux filtrer la carte par région afin de gérer mes clubs | E54: 2 | F54: Backlog | G54: S3 | H54: • Filtres : région, sport, statut • Zoom/pan intuitif • Export de la carte en PNG • Intégration avec les alertes | I54: Monitoring & Infrastructure | J54: Planifié
A55: US-10.2.1 | B55: F-10.2 | C55: E-10 | D55: En tant qu'administrateur NEOPRO, je veux voir les métriques agrégées de toute la flotte afin d'avoir une vue d'ensemble de la santé du système | E55: 5 | F55: Terminé | G55: S1 | H55: • Dashboard avec KPIs : uptime global, nb vidéos diffusées, bande passante • SLA : 99% uptime • Comparaison par région/opérateur • Export mensuel automatique | I55: Monitoring & Infrastructure | J55: Planifié
... A64: US-13.1.2 | B64: F-13.1 | C64: E-13 | D64: En tant qu'administrateur NEOPRO, je veux gérer les templates de thèmes afin de garantir une expérience cohérente | E64: 2 | F64: Backlog | G64: S2 | H64: • Création de thèmes maîtres par sport • Guidelines de branding • Validation du contraste/lisibilité • Versioning des thèmes | I64: Expérience Match | J64: Planifié
A65: US-14.1.1 | B65: F-14.1 | C65: E-14 | D65: En tant qu'opérateur, je veux contribuer à un fonds de solidarité afin de soutenir les petits clubs en difficulté | E65: 3 | F65: Backlog | H65: • Pourcentage de revenus pub à reverser • Configuration flexible du taux • Transparent : voir où va l'argent • Rapport mensuel de contribution | I65: Sponsors & Monétisation | J65: Planifié
A66: US-14.1.2 | B66: F-14.1 | C66: E-14 | D66: En tant qu'administrateur NEOPRO, je veux gérer le fonds de solidarité afin d'aider les clubs en difficulté | E66: 3 | F66: Backlog | H66: • Interface d'allocation du fonds • Critères d'éligibilité des bénéficiaires • Approbation des dossiers • Audit trail des dépenses | I66: Sponsors & Monétisation | J66: Planifié
A67: US-15.1.1 | B67: F-15.1 | C67: E-15 | D67: En tant qu'opérateur, je veux importer automatiquement les calendriers des fédérations afin de synchroniser les matchs | E67: 5 | F67: Backlog | H67: • Intégration API FFB (basket), FFH (handball), etc. • Synchronisation quotidienne • Mapping automatique des compétitions • Alertes de conflit de calendrier • Historique des imports | I67: Expérience Match | J67: Planifié
A68: US-15.1.2 | B68: F-15.1 | C68: E-15 | D68: En tant qu'administrateur NEOPRO, je veux gérer les connecteurs de fédération afin de supporter de nouveaux sports | E68: 3 | F68: Backlog | H68: • Création de connecteurs pour nouvelles APIs • Tests d'intégrité des données • Documentation du processus • Support multi-fédérations par club | I68: Expérience Match | J68: Planifié
A69: US-16.1.1 | B69: F-16.1 | C69: E-16 | D69: En tant qu'opérateur, je veux recevoir un rapport mensuel automatique afin de suivre la performance sans action manuelle | E69: 2 | F69: Backlog | G69: S3 | H69: • Email automatique le 1er du mois • Contenu : uptime, vidéos diffusées, revenus • Attachement PDF formaté • Lien pour accéder au dashboard détaillé | I69: Analytics & Reporting | J69: Planifié
A70: US-16.1.2 | B70: F-16.1 | C70: E-16 | D70: En tant qu'annonceur, je veux recevoir un rapport mensuel de mes vidéos afin de suivre mon ROI | E70: 2 | F70: Backlog | G70: S3 | H70: • Email personnalisé avec logo • KPIs : impressions, clics, CTR • Comparaison mois précédent • Recommandations d'optimisation | I70: Analytics & Reporting | J70: Planifié
A71: US-17.1.1 | B71: F-17.1 | C71: E-17 | D71: En tant qu'annonceur, je veux tester deux versions de ma vidéo afin d'optimiser le CTR | E71: 5 | F71: Backlog | H71: • Interface de création d'A/B test • Répartition 50/50 du trafic • Durée min du test : 7 jours • Dashboard de statistiques en temps réel • Test statistique (chi-2) • Recommandation de variante gagnante | I71: Sponsors & Monétisation | J71: Planifié
A72: US-17.1.2 | B72: F-17.1 | C72: E-17 | D72: En tant qu'administrateur NEOPRO, je veux auditer les A/B tests afin de respecter les normes de qualité | E72: 2 | F72: Backlog | H72: • Dashboard d'ensemble des tests actifs • Détection de tests biaisés • Historique des résultats • Recommandations d'optimisation | I72: Sponsors & Monétisation | J72: Planifié
A73: US-18.1.1 | B73: F-18.1 | C73: E-18 | D73: En tant qu'opérateur, je veux importer les données de billetterie pour connaître l'audience réelle afin de facturer plus précisément | E73: 5 | F73: Backlog | H73: • Import de fichiers de billetterie (CSV, API) • Deduplication des spectateurs • Synchronisation avec les matchs • Rapports d'audience détaillés • Archivage des données | I73: Expérience Match | J73: Planifié
A74: US-18.1.2 | B74: F-18.1 | C74: E-18 | D74: En tant qu'annonceur, je veux connaître l'audience réelle de mes vidéos afin d'ajuster mon tarif | E74: 3 | F74: Backlog | H74: • Impression par spectateur (pas par heure) • Facteurs de confiance (billetterie confirmée) • Données historiques exploitables • Estimations pour matchs futurs | I74: Expérience Match | J74: Planifié
A75: US-19.1.1 | B75: F-19.1 | C75: E-19 | D75: En tant qu'opérateur, je veux compter automatiquement les spectateurs avec une caméra afin de capturer l'audience en temps réel | E75: 5 | F75: Backlog | H75: • Intégration caméra USB ou IP • Détection de personnes par IA (TensorFlow) • Calibration par gymnase (FOV) • Comptage continu avec buffer local • Upload batch toutes les heures | I75: Expérience Match | J75: Planifié
A76: US-19.1.2 | B76: F-19.1 | C76: E-19 | D76: En tant qu'administrateur NEOPRO, je veux valider et optimiser le comptage afin d'assurer la qualité | E76: 3 | F76: Backlog | H76: • Dashboard de validation des comptages • Détection d'anomalies (pics aberrants) • Calibrage fin par environnement • Rapports de précision | I76: Expérience Match | J76: Planifié
A77: US-20.1.1 | B77: F-20.1 | C77: E-20 | D77: En tant qu'administrateur NEOPRO, je veux prédire les défaillances Pi afin d'intervenir avant la panne | E77: 5 | F77: Backlog | H77: • Modèle ML (Random Forest) sur l'historique • Features : CPU, mémoire, temp, signal WiFi • Prédiction 24-48h en avance • Alertes proactives • Précision min 80% | I77: Monitoring & Infrastructure | J77: Planifié
A78: US-20.1.2 | B78: F-20.1 | C78: E-20 | D78: En tant qu'annonceur, je veux prédire l'engagement de ma vidéo afin d'optimiser le budget | E78: 3 | F78: Backlog | H78: • Prédiction CTR basée sur historique • Recommandations de créatifs performants • Estimation du ROI par club • A/B test suggestions | I78: Monitoring & Infrastructure | J78: Planifié
A79: US-21.1.1 | B79: F-21.1 | C79: E-21 | D79: En tant que partenaire intégré, je veux accéder à l'API Neopro via OAuth 2.0 afin d'intégrer les données dans ma plateforme | E79: 5 | F79: Backlog | H79: • Implémentation OAuth 2.0 Authorization Code • Scopes : read:sites, read:metrics, write:videos • Rate limiting par client • Documentation Swagger • Sandbox de test | I79: Sponsors & Monétisation | J79: Planifié
A80: US-21.1.2 | B80: F-21.1 | C80: E-21 | D80: En tant qu'administrateur NEOPRO, je veux gérer les tokens de partenaires afin de sécuriser les accès | E80: 3 | F80: Backlog | H80: • Interface de création/révocation de tokens • Audit trail des appels API • Monitoring des quotas • Alertes d'usage anormal | I80: Sponsors & Monétisation | J80: Planifié
A81: US-IMP-ADM-01 | B81: HIST-ADM | C81: E-10 | D81: En tant qu'admin NEOPRO, je veux un système de jobs admin afin de planifier les tâches de maintenance | E81: 3 | F81: Livré | G81: Pré-PI | H81: Synchronisation fiable et atomique | Récupération en cas d'erreur réseau | I81: Administration & Infrastructure | J81: Livré
A82: US-IMP-ADM-02 | B82: HIST-ADM | C82: E-10 | D82: En tant qu'admin NEOPRO, je veux une télécommande cloud pour les sites afin de contrôler la TV à distance | E82: 3 | F82: Livré | G82: Pré-PI | H82: Fonctionnalité testée sur matériel réel | Performance acceptable | I82: Administration & Infrastructure | J82: Livré
A83: US-IMP-ADM-03 | B83: HIST-ADM | C83: E-10 | D83: En tant qu'admin NEOPRO, je veux créer des groupes de sites afin de gérer les déploiements par groupe | E83: 3 | F83: Livré | G83: Pré-PI | H83: Feature implémentée et testée | Documentation fournie | I83: Administration & Infrastructure | J83: Livré
A84: US-IMP-ADM-04 | B84: HIST-ADM | C84: E-10 | D84: En tant qu'admin NEOPRO, je veux envoyer des emails transactionnels afin de communiquer avec les utilisateurs | E84: 3 | F84: Livré | G84: Pré-PI | H84: Alertes détectées et envoyées | Notifications reçues correctement | I84: Administration & Infrastructure | J84: Livré
A85: US-IMP-ADM-05 | B85: HIST-ADM | C85: E-10 | D85: En tant qu'admin NEOPRO, je veux un gestionnaire de mémoire optimisé afin d'éviter les fuites | E85: 5 | F85: Livré | G85: Pré-PI | H85: Feature implémentée et testée | Documentation fournie | I85: Administration & Infrastructure | J85: Livré
A86: US-IMP-ADM-06 | B86: HIST-ADM | C86: E-10 | D86: En tant qu'admin NEOPRO, je veux utiliser le cache mémoire pour les opérations fréquentes afin d'améliorer les performances | E86: 3 | F86: Livré | G86: Pré-PI | H86: Feature implémentée et testée | Documentation fournie | I86: Administration & Infrastructure | J86: Livré
A87: US-IMP-ADM-07 | B87: HIST-ADM | C87: E-10 | D87: En tant qu'admin NEOPRO, je veux nettoyer automatiquement la mémoire GPU afin d'éviter les fuites | E87: 3 | F87: Livré | G87: Pré-PI | H87: Feature implémentée et testée | Documentation fournie | I87: Administration & Infrastructure | J87: Livré
A88: US-IMP-ADM-08 | B88: HIST-ADM | C88: E-10 | D88: En tant qu'admin NEOPRO, je veux que chaque utilisateur n'accède qu'aux données de ses clubs afin d'isoler complètement les tenants en base PostgreSQL | E88: 3 | F88: Livré | G88: Pré-PI | H88: Feature implémentée et testée | Documentation fournie | I88: Administration & Infrastructure | J88: Livré
A89: US-IMP-ADM-10 | B89: HIST-ADM | C89: E-10 | D89: En tant qu'admin NEOPRO, je veux une documentation OpenAPI Swagger afin de faciliter l'intégration de l'API | E89: 3 | F89: Livré | G89: Pré-PI | H89: Fonctionnalité testée sur matériel réel | Performance acceptable | I89: Administration & Infrastructure | J89: Livré
A90: US-IMP-ADM-11 | B90: HIST-ADM | C90: E-10 | D90: En tant qu'admin NEOPRO, je veux une vue cartographique des sites afin de visualiser leur répartition | E90: 3 | F90: Livré | G90: Pré-PI | H90: Feature implémentée et testée | Documentation fournie | I90: Administration & Infrastructure | J90: Livré
A91: US-IMP-ADM-12 | B91: HIST-ADM | C91: E-10 | D91: En tant qu'admin NEOPRO, je veux obtenir un diagnostic complet de la santé d'un Pi en format JSON afin de diagnostiquer rapidement | E91: 3 | F91: Livré | G91: Pré-PI | H91: Feature implémentée et testée | Documentation fournie | I91: Administration & Infrastructure | J91: Livré
A92: US-IMP-ADM-13 | B92: HIST-ADM | C92: E-10 | D92: En tant qu'admin NEOPRO, je veux une télécommande cloud pour les sites afin de contrôler la TV à distance | E92: 3 | F92: Livré | G92: Pré-PI | H92: Feature implémentée et testée | Documentation fournie | I92: Administration & Infrastructure | J92: Livré
... A254: US-IMP-USR-04 | B254: HIST-USR | C254: E-09 | D254: En tant qu'admin NEOPRO, je veux gérer les utilisateurs multi-tenant afin de contrôler les accès par rôle | E254: 5 | F254: Livré | G254: Pré-PI | H254: Interface admin fonctionnelle | Opérations effectuées avec succès | I254: Administration & Infrastructure | J254: Livré
A257: RÉSUMÉ
A258: Total US | B258: =COUNTA(A5:A254) -> 250
A259: SP Planifiés | B259: =SUMIF(J5:J254,"Planifié",E5:E254) -> 241
A260: SP Livrés | B260: =SUMIF(J5:J254,"Livré",E5:E254) -> 575
A261: SP Total | B261: =SUM(E5:E254) -> 816
A271: US-06.1.3 | B271: F-06.1 | C271: PI-1 S2 | D271: Auto-provisioning réseau Pi | E271: 5 | F271: To Do | G271: PI-1 S2

Sheet Implemented Backlog
A1: ← Dashboard | B1: IMPLEMENTED BACKLOG — 174 Features en Production
A2: 174 features — 13 domaines — Source: 34 changelogs + 200+ commits
A3: ID | B3: Feature | C3: Status | D3: Version | E3: Fichier | F3: Domaine
A4: IMP-SEC-01 | B4: Authentification JWT (HttpOnly cookies + Bearer) | C4: Production | D4: v1.0 | E4: auth.controller.ts | F4: Authentification & Sécurité
A5: IMP-SEC-02 | B5: MFA / 2FA (TOTP avec QR code) | C5: Production | D5: v1.0 | E5: mfa.service.ts | F5: Authentification & Sécurité
A6: IMP-SEC-03 | B6: Réinitialisation mot de passe (token 24h + email) | C6: Production | D6: v1.0 | E6: password-reset.service.ts | F6: Authentification & Sécurité
A7: IMP-SEC-04 | B7: Journalisation d'audit GDPR | C7: Production | D7: v1.0 | E7: audit.service.ts | F7: Authentification & Sécurité
A8: IMP-SEC-05 | B8: Sécurité niveau ligne (isolation multi-tenant PostgreSQL) | C8: Production | D8: v1.0 | E8: rls-functions.sql | F8: Authentification & Sécurité
A9: IMP-SEC-06 | B9: CORS fermé par défaut en production | C9: Production | D9: v1.0 | E9: server.ts | F9: Authentification & Sécurité
A10: IMP-SEC-07 | B10: Auth admin Raspberry (cookies session + mot de passe initial) | C10: Production | D10: v1.0 | E10: admin-server.js | F10: Authentification & Sécurité
A11: IMP-SEC-08 | B11: Suppression mot de passe en dur | C11: Production | D11: v1.0 | E11: - | F11: Authentification & Sécurité
A12: IMP-SEC-09 | B12: GDPR self-service (Art. 17 droit à l'effacement, Art. 20 portabilité) | C12: Production | D12: v1.0 | E12: gdpr.service.ts | F12: Authentification & Sécurité
A13: IMP-SEC-10 | B13: Sauvegardes chiffrées AES-256-GCM avec PBKDF2 | C13: Production | D13: v1.0 | E13: backup-encryption.service.ts | F13: Authentification & Sécurité
A14: IMP-SEC-11 | B14: Helmet renforcé (CSP, X-Frame-Options deny, HSTS 1 an) | C14: Production | D14: v1.0 | E14: server.ts | F14: Authentification & Sécurité
... A177: IMP-DOC-07 | B177: Documentation framework SAFe complète | C177: Production | D177: v3.60.0 | E177: docs/safe/ | F177: Documentation
A178: Statistiques Produit
A179: Features implémentées | B179: 184
A180: Domaines fonctionnels
A181: Controllers API | B181: 38
A182: Services métier | B182: 37
A183: Repositories | B183: 24
A184: Versions released | B184: 30+ (v1.0 → v3.60.0)
A185: Tests (total) | B185: 2 387
A186: ← Dashboard | B186: ← Features & US
A189: RÉSUMÉ PAR DOMAINE
A190: Domaine | B190: Nombre
A191: Admin & Configuration | B191: =COUNTIF(F:F,"Admin & Configuration") -> 23
A192: Analytics & Reporting | B192: =COUNTIF(F:F,"Analytics & Reporting") -> 17
A193: Authentification & Sécurité | B193: =COUNTIF(F:F,"Authentification & Sécurité") -> 13
A194: Content Management | B194: =COUNTIF(F:F,"Content Management") -> 12
A195: Diffusion & Playlists | B195: =COUNTIF(F:F,"Diffusion & Playlists") -> 3
A196: Documentation | B196: =COUNTIF(F:F,"Documentation") -> 6
A197: Déploiement & OTA | B197: =COUNTIF(F:F,"Déploiement & OTA") -> 11
A198: Monitoring & Alertes | B198: =COUNTIF(F:F,"Monitoring & Alertes") -> 22
A199: Overlay & Score Live | B199: =COUNTIF(F:F,"Overlay & Score Live") -> 9
A200: Raspberry Pi & Edge | B200: =COUNTIF(F:F,"Raspberry Pi & Edge") -> 23
A201: Réseau & Connectivité | B201: =COUNTIF(F:F,"Réseau & Connectivité") -> 18
A202: Sponsors & Régie | B202: =COUNTIF(F:F,"Sponsors & Régie") -> 13
A203: Utilisateurs & Rôles | B203: =COUNTIF(F:F,"Utilisateurs & Rôles") -> 4
A204: TOTAL | B204: =SUM(B191:B203) -> 174

Sheet ROAM
A1: ← Dashboard
A3: REGISTRE ROAM
A4: ID Risque | B4: Description | C4: Statut ROAM | D4: Probabilité | E4: Impact | F4: Responsable | G4: Échéance | H4: Action / Atténuation
A5: R-01 | B5: Capacité solo-dev insuffisante pour 81 SP engagés | C5: Accepté | D5: Haute | E5: Moyen | F5: Gwenvael | G5: Mars 2026 | H5: Recruter freelance si >60% capacité dépassée; MVP sponsors ultra-lean (portail self-service, 3 features max)
A6: R-02 | B6: WiFi gymnase instable pendant les tests | C6: Atténué | D6: Haute | E6: Moyen | F6: Gwenvael | G6: Fév 2026 | H6: Cache 48h déployé; mode hors-ligne fonctionnel; test terrain NLF validé; monitoring signal WiFi actif
A7: R-03 | B7: Aucun sponsor inscrit pour valider le portail | C7: Pris en charge | D7: Moyenne | E7: Élevé | F7: Gwenvael + Gabin | G7: Mars 2026 | H7: Démo portail en conditions réelles avec 1 sponsor beta; créer offre "early adopter" avec pricing attractif
A8: R-04 | B8: Dépendance Supabase pour le scaling | C8: Accepté | D8: Basse | E8: Élevé | F8: Gwenvael | G8: PI-2 | H8: Évaluer alternatives si pool saturé (>80%); plan migration PgBouncer si nécessaire
A9: R-05 | B9: Sécurité des api_keys Pi | C9: Atténué | D9: Basse | E9: Critique | F9: Gwenvael | G9: Continu | H9: Rotation SHA-256 trimestrielle; audit sécurité pré-PI-2; never change api_key format
A10: R-06 | B10: Retard onboarding automatisé bloque le scaling | C10: Pris en charge | D10: Moyenne | E10: Critique | F10: Gwenvael | G10: Mars 2026 | H10: Prioriser E-06 (auto-provisioning + wizard); time-to-live <1 jour objectif; golden image standardisée
A11: R-07 | B11: Hébergement FTP Hostinger comme point de défaillance | C11: Accepté | D11: Basse | E11: Élevé | F11: Gwenvael | G11: PI-3 | H11: Évaluer migration S3/CloudFront si >50 sites; backup cross-provider en place
A12: R-08 | B12: Absence de tests E2E sur le parcours sponsor | C12: Pris en charge | D12: Haute | E12: Moyen | F12: Gwenvael | G12: Mars 2026 | H12: Écrire tests Playwright parcours sponsor complet avant livraison PI-1; couvrir inscription→upload→validation→diffusion
A14: RÉSUMÉ ROAM
A15: Statut ROAM
A16: Résolu | B16: =COUNTIF(C5:C12,"Résolu") -> 0 | C16: =IFERROR(B16/B20,0) -> 0 | D16: █ Vert | F16: Critique | G16: =COUNTIF(E5:E12,"Critique") -> 2 | H16: =IFERROR(G16/G19,0) -> 0.25
A17: Pris en charge | B17: =COUNTIF(C5:C12,"Pris en charge") -> 3 | C17: =IFERROR(B17/B20,0) -> 0.375 | D17: █ Orange | F17: Élevé | G17: =COUNTIF(E5:E12,"Élevé") -> 3 | H17: =IFERROR(G17/G19,0) -> 0.375
A18: Accepté | B18: =COUNTIF(C5:C12,"Accepté") -> 3 | C18: =IFERROR(B18/B20,0) -> 0.375 | D18: █ Jaune | F18: Moyen | G18: =COUNTIF(E5:E12,"Moyen") -> 3 | H18: =IFERROR(G18/G19,0) -> 0.375
A19: Atténué | B19: =COUNTIF(C5:C12,"Atténué") -> 2 | C19: =IFERROR(B19/B20,0) -> 0.25 | D19: █ Bleu | F19: TOTAL | G19: =SUM(G16:G18) -> 8 | H19: =SUM(H16:H18) -> 1
A20: TOTAL | B20: =SUM(B16:B19) -> 8 | C20: =SUM(C16:C19) -> 1

Sheet PI Objectives
A1: PI Objectives — Scoring Business Value
A2: SAFe Essential — BV scoring 1-10 par Business Owners | Prédictibilité cible > 80% | O2: ← Dashboard
A4: Epics Done — BV acquise avant PI-1
A5: # | B5: Epic | C5: Description | D5: BV acquise | E5: Statut | F5: Preuve
A6: D1 | B6: E-04 | C6: Profils Config Match | D6: 7 | E6: ✅ Done | F6: config-profiles.controller.ts
A7: D2 | B7: E-08 | C7: Alertes Prédictives | D7: 6 | E7: ✅ Done | F7: predictive-alerts.service.ts
A8: D3 | B8: E-09 | C8: Architecture Audit | D8: 5 | E8: ✅ Done | F8: 24 repositories, ESLint
A9: D4 | B9: E-07 | C9: Résilience WiFi (partiel) | D9: 5 | E9: ⚠️ Partiel | F9: Cache 48h + monitoring OK, USB WiFi reste
A10: D5 | B10: E-10 | C10: Monitoring Fleet (partiel) | D10: 3 | E10: ⚠️ Partiel | F10: Métriques OK, carte Leaflet reste
C11: Total BV acquise | D11: 26
A13: PI-1 Objectives — Engagés (Fév-Mars 2026)
A14: # | B14: Objectif PI | C14: VS | D14: Thème | E14: BV (Planned) | F14: Features liées | G14: SP estimés | H14: BV Réel | I14: Atteint ? | J14: Commentaire
A15: 1 | B15: Lancer le portail sponsor self-service | C15: VS2 | D15: TS1 | E15: 9 | F15: F-01.1, F-01.2, F-01.3 | G15: 19
A16: 2 | B16: Livrer les analytics sponsors avec rapport PDF | C16: VS2 | D16: TS1 | E16: 10 | F16: F-03.1, F-03.2, F-03.3 | G16: 23
A17: 3 | B17: Implémenter la rotation sponsor équitable | C17: VS2 | D17: TS1 | E17: 8 | F17: F-02.1, F-02.2 | G17: 11
A18: 4 | B18: Créer le wizard onboarding club | C18: VS1 | D18: TS3 | E18: 10 | F18: F-06.1, F-06.2 | G18: 18
B19: Total Engagés | E19: 37 | G19: 71
A21: PI-1 Objectives — Étendus
A22: # | B22: Objectif PI | C22: VS | D22: Thème | E22: BV (Planned) | F22: Features liées | G22: SP estimés | H22: BV Réel | I22: Atteint ? | J22: Commentaire
A23: 5 | B23: Carte de la flotte Leaflet | C23: Transverse | D23: TS4 | E23: 4 | F23: F-10.1 | G23: 5
A24: 6 | B24: Support clé USB WiFi externe | C24: VS1 | D24: TS3 | E24: 3 | F24: F-07.3 | G24: 3
B25: Total Étendus | E25: 7 | G25: 8
A27: Récapitulatif PI-1
A28: Catégorie | B28: Objectifs | C28: SP | D28: BV total | E28: Capacité PI | F28: Taux charge
A29: Engagés | B29: 4 | C29: 71 | D29: 37 | E29: ~80 SP | F29: 89%
A30: Étendus | B30: 2 | C30: 8 | D30: 7
A31: Total PI-1 | B31: 6 | C31: 79 | D31: 44
A33: Calcul de Prédictibilité (à remplir en Inspect & Adapt)
A34: Objectif | B34: BV Planifié | C34: BV Réel | D34: Atteint ?
A35: 1. Portail sponsor | B35: 9
A36: 2. Analytics sponsors | B36: 10
A37: 3. Rotation sponsors | B37: 8
A38: 4. Wizard onboarding | B38: 10
A39: Total Engagés | B39: 37
A40: 5. Carte flotte (étendu) | B40: 4
A41: 6. USB WiFi (étendu) | B41: 3
A42: Total Étendus | B42: 7
A43: Prédictibilité Programme = BV Réel / 37 → Cible > 80%
A45: PI-2 Objectives (prévisionnel — Avr-Mai 2026)
A46: # | B46: Objectif PI (prévisionnel) | C46: VS | D46: Thème | E46: BV estimé
A47: 1 | B47: Lancer la régie publicitaire régionale avec ≥ 1 annonceur signé | C47: VS2 | D47: TS1 | E47: 10
A48: 2 | B48: Livrer 3 templates motion design personnalisables | C48: VS2 | D48: TS2 | E48: 6
A49: 3 | B49: Carry-over PI-1 (objectifs étendus non atteints) | C49: - | D49: - | E49: Variable
A51: PI-3 Objectives (prévisionnel — Juin-Juil 2026)
A52: # | B52: Objectif PI (prévisionnel) | C52: VS | D52: Thème | E52: BV estimé
A53: 1 | B53: Multi-écrans synchronisés (2 Pi par site) | C53: VS1 | D53: TS2 | E53: 8
A54: 2 | B54: Marque blanche club fonctionnelle | C54: VS1 | D54: TS2 | E54: 6
A55: 3 | B55: Fonds de solidarité sport lancé | C55: Transverse | D55: TS3 | E55: 5

Sheet Sprint Tracker
A1: Sprint Tracker — PI-1 à PI-3
A2: SAFe Essential — 3 sprints × 2 semaines par PI | Capacité ~26 SP/sprint | J2: ← Dashboard
A4: PI-1 — Fév-Mars 2026 (79 SP planifiés)
A5: Sprint | B5: Dates | C5: SP Planifiés | D5: SP Réalisés | E5: US Planifiées | F5: US Terminées | G5: Bugs | H5: Vélocité % | I5: Notes
A6: S1 | B6: Sem 8-9 (Fév 16-27) | C6: 26 | D6: =SUMIFS('User Stories'!E:E,'User Stories'!G:G,A6,'User Stories'!J:J,"Planifié",'User Stories'!F:F,"Terminé")+SUMIFS('User Stories'!E:E,'User Stories'!G:G,A6,'User Stories'!J:J,"Planifié",'User Stories'!F:F,"Livré") -> 38 | E6: =COUNTIFS('User Stories'!G:G,A6,'User Stories'!J:J,"Planifié") -> 9 | F6: =COUNTIFS('User Stories'!G:G,A6,'User Stories'!J:J,"Planifié",'User Stories'!F:F,"Terminé")+COUNTIFS('User Stories'!G:G,A6,'User Stories'!J:J,"Planifié",'User Stories'!F:F,"Livré") -> 9 | I6: Sponsors setup + Architecture
A7: S2 | B7: Sem 10-11 (Mar 2-13) | C7: 25 | D7: =SUMIFS('User Stories'!E:E,'User Stories'!G:G,A7,'User Stories'!J:J,"Planifié",'User Stories'!F:F,"Terminé")+SUMIFS('User Stories'!E:E,'User Stories'!G:G,A7,'User Stories'!J:J,"Planifié",'User Stories'!F:F,"Livré") -> 23 | E7: =COUNTIFS('User Stories'!G:G,A7,'User Stories'!J:J,"Planifié") -> 23 | F7: =COUNTIFS('User Stories'!G:G,A7,'User Stories'!J:J,"Planifié",'User Stories'!F:F,"Terminé")+COUNTIFS('User Stories'!G:G,A7,'User Stories'!J:J,"Planifié",'User Stories'!F:F,"Livré") -> 8 | I7: Analytics + Onboarding
A8: S3 | B8: Sem 12-13 (Mar 16-27) | C8: 28 | D8: =SUMIFS('User Stories'!E:E,'User Stories'!G:G,A8,'User Stories'!J:J,"Planifié",'User Stories'!F:F,"Terminé")+SUMIFS('User Stories'!E:E,'User Stories'!G:G,A8,'User Stories'!J:J,"Planifié",'User Stories'!F:F,"Livré") -> 16 | E8: =COUNTIFS('User Stories'!G:G,A8,'User Stories'!J:J,"Planifié") -> 22 | F8: =COUNTIFS('User Stories'!G:G,A8,'User Stories'!J:J,"Planifié",'User Stories'!F:F,"Terminé")+COUNTIFS('User Stories'!G:G,A8,'User Stories'!J:J,"Planifié",'User Stories'!F:F,"Livré") -> 5 | I8: Intégration + Polish
A9: Total PI-1 | C9: =SUM(C6:C8) -> 79 | D9: =SUM(D6:D8) -> 77 | E9: =SUM(E6:E8) -> 54
A11: PI-2 — Avr-Mai 2026 (61 SP planifiés)
A12: Sprint | B12: Dates | C12: SP Planifiés | D12: SP Réalisés | E12: US Planifiées | F12: US Terminées | G12: Bugs | H12: Vélocité % | I12: Notes
A13: S4 | B13: Sem 14-15 (Avr 1-11) | C13: 20 | D13: =SUMIFS('User Stories'!E:E,'User Stories'!G:G,A13,'User Stories'!J:J,"Planifié",'User Stories'!F:F,"Terminé")+SUMIFS('User Stories'!E:E,'User Stories'!G:G,A13,'User Stories'!J:J,"Planifié",'User Stories'!F:F,"Livré") -> 0 | E13: =COUNTIFS('User Stories'!G:G,A13,'User Stories'!J:J,"Planifié") -> 0 | F13: =COUNTIFS('User Stories'!G:G,A13,'User Stories'!J:J,"Planifié",'User Stories'!F:F,"Terminé")+COUNTIFS('User Stories'!G:G,A13,'User Stories'!J:J,"Planifié",'User Stories'!F:F,"Livré") -> 0 | I13: Régie publicitaire
A14: S5 | B14: Sem 16-17 (Avr 14-25) | C14: 21 | D14: =SUMIFS('User Stories'!E:E,'User Stories'!G:G,A14,'User Stories'!J:J,"Planifié",'User Stories'!F:F,"Terminé")+SUMIFS('User Stories'!E:E,'User Stories'!G:G,A14,'User Stories'!J:J,"Planifié",'User Stories'!F:F,"Livré") -> 0 | E14: =COUNTIFS('User Stories'!G:G,A14,'User Stories'!J:J,"Planifié") -> 0 | F14: =COUNTIFS('User Stories'!G:G,A14,'User Stories'!J:J,"Planifié",'User Stories'!F:F,"Terminé")+COUNTIFS('User Stories'!G:G,A14,'User Stories'!J:J,"Planifié",'User Stories'!F:F,"Livré") -> 0 | I14: Motion design + Score Live
A15: S6 | B15: Sem 18-19 (Avr 28-Mai 9) | C15: 20 | D15: =SUMIFS('User Stories'!E:E,'User Stories'!G:G,A15,'User Stories'!J:J,"Planifié",'User Stories'!F:F,"Terminé")+SUMIFS('User Stories'!E:E,'User Stories'!G:G,A15,'User Stories'!J:J,"Planifié",'User Stories'!F:F,"Livré") -> 0 | E15: =COUNTIFS('User Stories'!G:G,A15,'User Stories'!J:J,"Planifié") -> 0 | F15: =COUNTIFS('User Stories'!G:G,A15,'User Stories'!J:J,"Planifié",'User Stories'!F:F,"Terminé")+COUNTIFS('User Stories'!G:G,A15,'User Stories'!J:J,"Planifié",'User Stories'!F:F,"Livré") -> 0 | I15: Email auto + A/B test
A16: Total PI-2 | C16: =SUM(C13:C15) -> 61 | D16: =SUM(D13:D15) -> 0
A18: PI-3 — Juin-Juil 2026 (51 SP planifiés)
A19: Sprint | B19: Dates | C19: SP Planifiés | D19: SP Réalisés | E19: US Planifiées | F19: US Terminées | G19: Bugs | H19: Vélocité % | I19: Notes
A20: S7 | B20: Sem 23-24 (Juin 1-12) | C20: 17 | D20: =SUMIFS('User Stories'!E:E,'User Stories'!G:G,A20,'User Stories'!J:J,"Planifié",'User Stories'!F:F,"Terminé")+SUMIFS('User Stories'!E:E,'User Stories'!G:G,A20,'User Stories'!J:J,"Planifié",'User Stories'!F:F,"Livré") -> 0 | E20: =COUNTIFS('User Stories'!G:G,A20,'User Stories'!J:J,"Planifié") -> 0 | F20: =COUNTIFS('User Stories'!G:G,A20,'User Stories'!J:J,"Planifié",'User Stories'!F:F,"Terminé")+COUNTIFS('User Stories'!G:G,A20,'User Stories'!J:J,"Planifié",'User Stories'!F:F,"Livré") -> 0 | I20: Multi-écrans + Marque blanche
A21: S8 | B21: Sem 25-26 (Juin 15-26) | C21: 17 | D21: =SUMIFS('User Stories'!E:E,'User Stories'!G:G,A21,'User Stories'!J:J,"Planifié",'User Stories'!F:F,"Terminé")+SUMIFS('User Stories'!E:E,'User Stories'!G:G,A21,'User Stories'!J:J,"Planifié",'User Stories'!F:F,"Livré") -> 0 | E21: =COUNTIFS('User Stories'!G:G,A21,'User Stories'!J:J,"Planifié") -> 0 | F21: =COUNTIFS('User Stories'!G:G,A21,'User Stories'!J:J,"Planifié",'User Stories'!F:F,"Terminé")+COUNTIFS('User Stories'!G:G,A21,'User Stories'!J:J,"Planifié",'User Stories'!F:F,"Livré") -> 0 | I21: Billetterie + Capteurs
A22: S9 | B22: Sem 27-28 (Juin 29-Juil 10) | C22: 17 | D22: =SUMIFS('User Stories'!E:E,'User Stories'!G:G,A22,'User Stories'!J:J,"Planifié",'User Stories'!F:F,"Terminé")+SUMIFS('User Stories'!E:E,'User Stories'!G:G,A22,'User Stories'!J:J,"Planifié",'User Stories'!F:F,"Livré") -> 0 | E22: =COUNTIFS('User Stories'!G:G,A22,'User Stories'!J:J,"Planifié") -> 0 | F22: =COUNTIFS('User Stories'!G:G,A22,'User Stories'!J:J,"Planifié",'User Stories'!F:F,"Terminé")+COUNTIFS('User Stories'!G:G,A22,'User Stories'!J:J,"Planifié",'User Stories'!F:F,"Livré") -> 0 | I22: ML + OAuth + Solidarité
A23: Total PI-3 | C23: 51 | D23: =SUM(D20:D22) -> 0
A25: Capacité de l'équipe
A26: Membre | B26: Rôle | C26: Capacité (SP/sprint) | D26: Spécialité | E26: Disponibilité
A27: Gwenvael | B27: Tech Lead / PO | C27: 18 | D27: Backend, Architecture, API | E27: 80% (PO + dev)
A28: Gabin | B28: Frontend Dev | C28: 8 | D28: Angular, UI/UX, Dashboard | E28: 100%
A29: Total | C29: 26
A31: Métriques Vélocité
A32: Métrique | B32: Valeur | C32: Cible | D32: Commentaire
A33: Vélocité moyenne cible | B33: ~26 SP/sprint | C33: 26 SP | D33: Basé sur capacité 2 devs
A34: US par sprint (cible) | B34: 6-7 US | C34: > 5 | D34: Fibonacci average 3-5 SP/US
A35: Taux de complétion | B35: à mesurer | C35: > 85% | D35: US terminées / US planifiées
A36: Carry-over max | C36: < 15% | D36: SP reportés vers sprint suivant

Sheet Inspect & Adapt
A1: Inspect & Adapt — NEOPRO
A2: Fréquence: fin de chaque PI (6 sem.) | Durée: 1h | Participants: Gwenvael, Gabin | I2: ← Dashboard
A4: AGENDA I&A (1h)
A5: Phase | B5: Durée | C5: Activité
A6: 1. Démo Système PI | B6: 15 min | C6: Démo des features livrées pendant le PI
A7: 2. Revue Quantitative | B7: 15 min | C7: Analyse des métriques (vélocité, prédictibilité, flow)
A8: 3. Rétrospective | B8: 20 min | C8: Ce qui a bien fonctionné / ce qui doit évoluer
A9: 4. Résolution de Problème | B9: 10 min | C9: Identifier le problème N°1 + action corrective
A11: I&A PI-1 — Phase 1: Démo Système (fin Mars 2026)
A12: Périmètre: E-01, E-02, E-03, E-06 + reliquats E-07/E-10
A13: Objectifs Engagés
A14: # | B14: Objectif PI | C14: Epic | D14: BV Planifié | E14: Livré ? | F14: BV Réel | G14: Commentaire | H14: Features liées
A15: 1 | B15: Portail sponsor self-service | C15: E-01 | D15: ='PI Objectives'!E15 -> 9 | H15: F-01.1, F-01.2, F-01.3
A16: 2 | B16: Analytics sponsors + rapport PDF | C16: E-03 | D16: ='PI Objectives'!E16 -> 10 | H16: F-03.1, F-03.2, F-03.3
A17: 3 | B17: Rotation sponsors équitable | C17: E-02 | D17: ='PI Objectives'!E17 -> 8 | H17: F-02.1, F-02.2
A18: 4 | B18: Wizard onboarding club | C18: E-06 | D18: ='PI Objectives'!E18 -> 10 | H18: F-06.1, F-06.2
A19: Objectifs Non-engagés (aspirationnels)
A20: # | B20: Objectif PI | C20: Epic | D20: BV Planifié | E20: Livré ? | F20: BV Réel | G20: Commentaire | H20: Features liées
A21: 5 | B21: WiFi USB auto-détection (reliquat) | C21: E-07 | D21: ='PI Objectives'!E23 -> 4 | H21: F-07.3
A22: 6 | B22: Carte flotte temps réel (reliquat) | C22: E-10 | D22: ='PI Objectives'!E24 -> 3 | H22: F-10.1
A24: Features à démontrer (12)
A25: • F-01.1 Inscription sponsor self-service | E25: • F-01.2 Upload vidéo sponsor + sélection gymnases
A26: • F-01.3 Validation admin des spots | E26: • F-02.1 Algorithme rotation round-robin
A27: • F-02.2 Configuration rotation par site | E27: • F-03.1 Dashboard analytics impressions
A28: • F-03.2 Export CSV + rapport PDF | E28: • F-03.3 Heatmap Leaflet impressions
A29: • F-06.1 Auto-provisioning Pi | E29: • F-06.2 Wizard onboarding 4 étapes
A30: • F-07.3 WiFi USB auto-détection (reliquat) | E30: • F-10.1 Carte flotte (reliquat)
A32: I&A PI-1 — Phase 2: Revue Quantitative
A33: Vélocité
A34: Sprint | B34: Dates | C34: SP Planifiés | D34: SP Complétés | E34: Vélocité % | F34: US Terminées | G34: US Reportées
A35: Sprint 1 | B35: Sem 8-9 | C35: ='Sprint Tracker'!C6 -> 26 | D35: ='Sprint Tracker'!D6 -> 38 | E35: =IF(C35=0,"-",D35/C35) -> 1.4615385 | F35: ='Sprint Tracker'!F6 -> 9 | G35: ='Sprint Tracker'!E6-F35 -> 0
A36: Sprint 2 | B36: Sem 10-11 | C36: ='Sprint Tracker'!C7 -> 25 | D36: ='Sprint Tracker'!D7 -> 23 | E36: =IF(C36=0,"-",D36/C36) -> 0.92 | F36: ='Sprint Tracker'!F7 -> 8 | G36: ='Sprint Tracker'!E7-F36 -> 15
A37: Sprint 3 | B37: Sem 12-13 | C37: ='Sprint Tracker'!C8 -> 28 | D37: ='Sprint Tracker'!D8 -> 16 | E37: =IF(C37=0,"-",D37/C37) -> 0.57142857 | F37: ='Sprint Tracker'!F8 -> 5 | G37: ='Sprint Tracker'!E8-F37 -> 17
A38: Total PI | C38: =SUM(C35:C37) -> 79 | D38: =SUM(D35:D37) -> 77 | E38: =IF(C38=0,"-",D38/C38) -> 0.97468354 | F38: =SUM(F35:F37) -> 22 | G38: =SUM(G35:G37) -> 32
A39: Vélocité moyenne: _ SP/sprint (cible: ~26) | Taux complétion US: _% (cible: >85%) | Carry-over: _% (cible: <15%)
A41: Prédictibilité Programme
A42: σ bv réel (engagés atteints) / σ bv planifié (engagés) = ___ / 37 → Cible > 80%
A44: Qualité
A45: Métrique | B45: Valeur avant PI | C45: Valeur fin PI | D45: Cible
A46: Tests central-server | B46: 1464 | D46: ≥ 1464
A47: Tests Angular Dashboard | B47: 554 | D47: ≥ 554
A48: Smoke tests | B48: 142 | D48: 142/142
A49: Tests Admin Pi | B49: 146 | D49: ≥ 146
A50: Tests Socket Pi | B50: 71 | D50: ≥ 71
A51: Total tests | B51: 2235 | D51: ≥ 2235
A52: Bugs post-release | B52: - | D52: < 3
A54: Flow Metrics
A55: Métrique | B55: Valeur PI-1 | C55: Cible | D55: Tendance
A56: Flow Velocity | B56: _ items/sprint | C56: 8 | D56: N/A (PI-1)
A57: Flow Time | B57: _ jours | C57: < 10
A58: Flow Load | B58: _ items WIP | C58: < 5
A59: Flow Efficiency | B59: _% | C59: > 30%
A60: Flow Distribution | C60: 60/15/15/10
A62: Temps de Cycle
A63: Métrique | B63: Valeur | C63: Cible
A64: Temps de cycle moyen (PR → fusionnée) | B64: _ jours | C64: < 3 jours
A65: Délai feature (début Epic → déployé) | B65: _ jours | C65: < 14 jours
A66: Temps moyen en revue de code | B66: _ heures | C66: < 4 heures
A67: Note: Solo-dev → cycle PR quasi-instantané. Le délai feature est la métrique clé.
A69: I&A PI-1 — Phase 3: Rétrospective (20 min)
A70: Ce qui a bien fonctionné ✅ | E70: Ce qui doit évoluer ⚠️
A71: 1. _à compléter en fin de PI_ | E71: 1. _à compléter en fin de PI_
A72: 2. _à compléter en fin de PI_ | E72: 2. _à compléter en fin de PI_
A73: 3. _à compléter en fin de PI_ | E73: 3. _à compléter en fin de PI_
A75: Mise à jour ROAM
A76: Risque | B76: Statut début PI | C76: Nouveau statut | D76: Action
A77: R-01 Capacité solo-dev | B77: Accepted | D77: Solo-dev reste la contrainte principale
A78: R-02 WiFi instable | B78: Mitigated | D78: WiFi USB 4 couches stabilisé en pré-PI-1
A79: R-03 Aucun sponsor beta | B79: Owned | D79: Portail sponsor E-01 en PI-1
A80: R-04 Supabase scaling | B80: Accepted | D80: Transaction mode, pool 5
A81: R-05 Sécurité api_keys | B81: Mitigated | D81: JWT + MFA + audit en place
A82: R-06 Retard onboarding | B82: Owned | D82: Wizard E-06 en PI-1
A83: R-07 FTP Hostinger SPOF | B83: Accepted | D83: ADR-025 dual storage planifié
A84: R-08 Tests E2E sponsor | B84: Owned | D84: Playwright E2E en PI-1 si capacité
A86: I&A PI-1 — Phase 4: Résolution de Problème (10 min)
A87: Étape | B87: Détail
A88: Accord sur le problème | B88: _description factuelle_
A89: Analyse cause racine (5 Pourquoi) | B89: _5 Pourquoi ou Ishikawa_
A90: Identifier la cause principale | B90: _cause racine retenue_
A91: Reformuler le problème | B91: _reformulé avec cause racine_
A92: Brainstormer des solutions | B92: 1. _ / 2. _ / 3. _
A93: Sélectionner et s'engager | B93: _solution + responsable + échéance_
A95: Décisions pour PI-2
A96: Décision | B96: Détail
A97: Report US vers PI-2 | B97: _US reportées_
A98: Ajustement capacité | B98: _vélocité réelle → nouvelle capacité PI-2_
A99: Nouveaux risques | B99: _ajoutés au ROAM PI-2_
A100: Ajustement périmètre PI-2 | B100: Prévu: E-05, E-11, E-15, E-16, E-17 (69 SP)
A101: Amélioration processus | B101: _action corrective_
A103: Historique I&A
A104: PI | B104: Date | C104: Prédictibilité | D104: Vélocité moy. | E104: Problème N°1 | F104: Action corrective
A105: PI-1 | B105: Mars 2026
A106: PI-2 | B106: Mai 2026
A107: PI-3 | B107: Juillet 2026

Sheet Flow Metrics
A1: Flow Metrics — Value Stream Level
A2: ← Dashboard
A4: LES 6 FLOW METRICS (SAFe 6.0)
A5: Métrique | B5: Définition | C5: Unité | D5: Cible PI-1
A6: Flow Distribution | B6: Répartition par type (feature, enabler, defect, debt) | C6: % | D6: 60/15/15/10
A7: Flow Velocity | B7: Items complétés par unité de temps | C7: items/sprint | D7: 8
A8: Flow Time | B8: Temps entrée → complétion d'un item | C8: jours | D8: < 10
A9: Flow Load | B9: Items en cours (WIP) | C9: items | D9: < 5
A10: Flow Efficiency | B10: % temps actif vs total | C10: % | D10: > 30%
A11: Flow Predictability | B11: Variation vélocité entre sprints | C11: écart-type | D11: < 20%
A13: FLOW DISTRIBUTION DVS-1 (PI-1)
A14: Type | B14: Epics | C14: SP | D14: %
A15: Feature | B15: E-01, E-02, E-03, E-04 | C15: 63 | D15: =IF(C19=0,"-",C15/C19) -> 0.49606299
A16: Enabler | B16: E-06, E-07, E-08, E-10 | C16: 51 | D16: =IF(C19=0,"-",C16/C19) -> 0.4015748
A17: Defect | B17: Buffer bugs production | C17: 5 | D17: =IF(C19=0,"-",C17/C19) -> 0.039370079
A18: Debt | B18: E-09 (Architecture Audit) | C18: 8 | D18: =IF(C19=0,"-",C18/C19) -> 0.062992126
A19: Total | C19: =SUM(C15:C18) -> 127 | D19: =SUM(D15:D18) -> 1
A21: FLOW DISTRIBUTION OVS-1 — Club to Screen
A22: Type | B22: Items planifiés | C22: SP | D22: % du total
A23: Feature | B23: E-04 (Profils), E-06 (Onboarding) | C23: 28 | D23: =IF(C27=0,"-",C23/C27) -> 0.73684211
A24: Enabler | B24: E-07 (WiFi V2) | C24: 10 | D24: =IF(C27=0,"-",C24/C27) -> 0.26315789
A25: Defect | B25: - | C25: 0 | D25: =IF(C27=0,"-",C25/C27) -> 0
A26: Debt | B26: - | C26: 0 | D26: =IF(C27=0,"-",C26/C27) -> 0
A27: Total | B27: 3 Epics | C27: 38 | D27: =IF(C27=0,"-",SUM(D23:D26)) -> 1
A29: FLOW DISTRIBUTION OVS-2 — Sponsor to Impression
A30: Type | B30: Items planifiés | C30: SP | D30: % du total
A31: Feature | B31: E-01 (Portail), E-02 (Rotation), E-03 (Analytics) | C31: 53 | D31: =IF(C35=0,"-",C31/C35) -> 1
A32: Enabler | B32: - | C32: 0 | D32: =IF(C35=0,"-",C32/C35) -> 0
A33: Defect | B33: - | C33: 0 | D33: =IF(C35=0,"-",C33/C35) -> 0
A34: Debt | B34: - | C34: 0 | D34: =IF(C35=0,"-",C34/C35) -> 0
A35: Total | B35: 3 Epics | C35: 53 | D35: =IF(C35=0,"-",SUM(D31:D34)) -> 1
A37: WIP LIMITS
A38: Colonne | B38: WIP Limit | C38: Justification
A39: Analysis | B39: 2 | C39: Solo dev → limiter le multitasking
A40: Dev | B40: 3 | C40: Max 3 US en parallèle (1 complexe + 2 simples)
A41: Review & Test | B41: 2 | C41: Code review solo → auto-review + tests
A42: Total WIP | B42: 5 | C42: Solo dev: 5 items max en cours
A44: LEAD TIME OVS-1 — Club to Screen
A45: Étape | B45: Temps actuel | C45: Cible fin PI-1 | D45: Cible PI-2
A46: Club signe → Envoi boîtier | B46: 2-3 jours | C46: 1 jour | D46: Même jour
A47: Envoi → Installation | B47: 3-5 jours (postal) | C47: 3-5 jours | D47: 1-2 jours
A48: Installation → Config | B48: 2-3 heures (SSH) | C48: 30 min (wizard) | D48: 15 min
A49: Config → Premier contenu | B49: 1 heure | C49: 30 min | D49: 10 min
A50: Total Lead Time | B50: 7-12 jours | C50: 5-7 jours | D50: 2-3 jours
A52: LEAD TIME OVS-2 — Sponsor to Impression
A53: Étape | B53: Temps actuel | C53: Cible fin PI-1 | D53: Cible PI-2
A54: Sponsor → Compte créé | B54: 1-2 semaines | C54: < 1 jour | D54: < 1 heure
A55: Upload spot → Validation | B55: 48h (email) | C55: < 4h (dashboard) | D55: < 1h
A56: Validation → Première diffusion | B56: 24h | C56: < 2h | D56: Immédiat
A57: Match → Rapport disponible | B57: Jamais (manuel) | C57: J+1 (auto) | D57: Temps réel
A58: Total Lead Time | B58: 2-3 semaines | C58: 2-3 jours | D58: < 1 jour
A60: TABLEAU DE BORD FLOW (Sprint Review)
A61: Sprint 1
A62: Métrique | B62: OVS-1 | C62: OVS-2 | D62: DVS-1 Global
A63: Items complétés
A64: Flow Time moyen
A65: WIP moyen
A66: Items bloqués (> 3j)
A67: Sprint 2
A68: Métrique | B68: OVS-1 | C68: OVS-2 | D68: DVS-1 Global
A69: Items complétés
A70: Flow Time moyen
A71: WIP moyen
A72: Items bloqués (> 3j)
A73: Sprint 3
A74: Métrique | B74: OVS-1 | C74: OVS-2 | D74: DVS-1 Global
A75: Items complétés
A76: Flow Time moyen
A77: WIP moyen
A78: Items bloqués (> 3j)

Sheet _ChartData
A1: Statut | B1: Epics | J1: Administration & Infrastructure | K1: OVS-1
A2: En cours | B2: =COUNTIF('Epics & LBC'!G:G,"En cours") -> 2 | J2: Analytics & Reporting | K2: OVS-2
A3: Terminé | B3: =COUNTIF('Epics & LBC'!G:G,"Terminé") -> 3 | J3: Architecture & Qualité | K3: OVS-1, OVS-2
A4: Backlog | B4: =COUNTIF('Epics & LBC'!G:G,"Backlog") -> 16 | J4: Authentification & Sécurité | K4: DVS-1
J5: Documentation & Qualité | K5: Transverse
A6: PI | B6: Story Points | J6: Déploiement & OTA
A7: PI-1 | B7: =SUMIF('Features & US'!I:I,"PI-1*",'Features & US'!E:E) -> 134 | J7: Expérience Match
A8: PI-2 | B8: =SUMIF('Features & US'!I:I,"PI-2*",'Features & US'!E:E) -> 61 | J8: Gestion de Contenu & Vidéo
A9: PI-3 | B9: =SUMIF('Features & US'!I:I,"PI-3*",'Features & US'!E:E) -> 51 | J9: Monitoring & Infrastructure
J10: Onboarding & Déploiement
A11: Sprint | B11: Actual SP | J11: Résilience & Edge
A12: S1 | B12: ='Sprint Tracker'!D4 -> 0 | J12: Sponsors & Monétisation
A13: S2 | B13: ='Sprint Tracker'!D5 -> SP Réalisés
A14: S3 | B14: ='Sprint Tracker'!D6 -> 38
A15: S4 | B15: ='Sprint Tracker'!D7 -> 23
A17: Domaine | B17: Allocation
A18: Monétisation | B18: 40
A19: Exp. Match | B19: 25
A20: Acquisition | B20: 20
A21: Excellence Ops | B21: 15

Sheet _Metadata
A1: _Metadata — Portfolio SAFe NEOPRO
A3: Clé | B3: Valeur
A4: Framework | B4: SAFe Essential (simplifié solo-dev)
A5: Entreprise | B5: NEOPRO
A6: Produit | B6: Système TV interactive clubs sportifs
A7: ART | B7: NEOPRO ART (1 équipe, 2 devs)
A8: PI Cadence | B8: 6 semaines (3 sprints × 2 semaines)
A9: PI actuel | B9: PI-1 (Fév-Mars 2026)
A10: Horizon | B10: PI-1 à PI-3 (Fév-Juil 2026)
A11: Value Streams | B11: VS1 (Infrastructure Club) + VS2 (Régie Sponsors)
A12: Source of Truth | B12: docs/safe/*.md (Git)
A13: Dernière mise à jour | B13: Février 2026
A14: Générateur | B14: export-to-excel.py + openpyxl
A15: Version | B15: 3.0
A17: Onglet | B17: Description | C17: Lignes | D17: Source MD
A18: Dashboard | B18: Navigation et résumé | D18: README.md
A19: Glossaire | B19: Termes SAFe et métier | D19: GLOSSARY.md
A20: Vision & OKR | B20: Vision produit et OKRs | D20: VISION-OKR.md
A21: Value Streams | B21: VS1 + VS2 avec thèmes | D21: VALUE-STREAMS.md
A22: Epics & LBC | B22: Backlog Epics avec WSJF | C22: 21 | D22: EPICS.md
A23: Lean Business Cases | B23: LBC détaillés par Epic | C23: 21 | D23: LEAN-BUSINESS-CASES.md
A24: Features & US | B24: Features groupées par Epic | C24: 35 | D24: FEATURES.md
A25: PI Objectives | B25: Objectives PI avec BV scoring | D25: PI-OBJECTIVES.md
A26: Sprint Tracker | B26: Suivi des sprints PI-1 | D26: SPRINT-TRACKER.md
A27: ROAM | B27: Risques et obstacles | C27: 8 | D27: ROAM.md
A28: Inspect & Adapt | B28: Template I&A fin de PI | D28: INSPECT-ADAPT.md
A29: Flow Metrics | B29: Métriques de flux SAFe | D29: FLOW-METRICS.md
A30: Implemented Backlog | B30: US implémentées (PI-0) | C30: 174 | D30: IMPLEMENTED-BACKLOG.md
A31: User Stories | B31: Toutes les US | C31: 250 | D31: USER-STORIES.md
